[
    {
        "provinsi": "82",
        "kabupaten": "8206",
        "kecamatan": "820610",
        "desa": "8206102005",
        "tps": "8206102005001",
        "url": "82\/8206\/820610\/8206102005\/8206102005001.json",
        "nama": "TPS 001, MABA SANGAJI, KOTA MABA, HALMAHERA TIMUR, MALUKU UTARA"
    },
    {
        "provinsi": "82",
        "kabupaten": "8206",
        "kecamatan": "820610",
        "desa": "8206102005",
        "tps": "8206102005002",
        "url": "82\/8206\/820610\/8206102005\/8206102005002.json",
        "nama": "TPS 002, MABA SANGAJI, KOTA MABA, HALMAHERA TIMUR, MALUKU UTARA"
    },
    {
        "provinsi": "82",
        "kabupaten": "8206",
        "kecamatan": "820610",
        "desa": "8206102005",
        "tps": "8206102005003",
        "url": "82\/8206\/820610\/8206102005\/8206102005003.json",
        "nama": "TPS 003, MABA SANGAJI, KOTA MABA, HALMAHERA TIMUR, MALUKU UTARA"
    },
    {
        "provinsi": "82",
        "kabupaten": "8206",
        "kecamatan": "820610",
        "desa": "8206102005",
        "tps": "8206102005004",
        "url": "82\/8206\/820610\/8206102005\/8206102005004.json",
        "nama": "TPS 004, MABA SANGAJI, KOTA MABA, HALMAHERA TIMUR, MALUKU UTARA"
    },
    {
        "provinsi": "82",
        "kabupaten": "8206",
        "kecamatan": "820610",
        "desa": "8206102005",
        "tps": "8206102005005",
        "url": "82\/8206\/820610\/8206102005\/8206102005005.json",
        "nama": "TPS 005, MABA SANGAJI, KOTA MABA, HALMAHERA TIMUR, MALUKU UTARA"
    },
    {
        "provinsi": "82",
        "kabupaten": "8206",
        "kecamatan": "820610",
        "desa": "8206102005",
        "tps": "8206102005006",
        "url": "82\/8206\/820610\/8206102005\/8206102005006.json",
        "nama": "TPS 006, MABA SANGAJI, KOTA MABA, HALMAHERA TIMUR, MALUKU UTARA"
    },
    {
        "provinsi": "82",
        "kabupaten": "8206",
        "kecamatan": "820610",
        "desa": "8206102005",
        "tps": "8206102005007",
        "url": "82\/8206\/820610\/8206102005\/8206102005007.json",
        "nama": "TPS 007, MABA SANGAJI, KOTA MABA, HALMAHERA TIMUR, MALUKU UTARA"
    },
    {
        "provinsi": "82",
        "kabupaten": "8206",
        "kecamatan": "820610",
        "desa": "8206102005",
        "tps": "8206102005008",
        "url": "82\/8206\/820610\/8206102005\/8206102005008.json",
        "nama": "TPS 008, MABA SANGAJI, KOTA MABA, HALMAHERA TIMUR, MALUKU UTARA"
    },
    {
        "provinsi": "82",
        "kabupaten": "8206",
        "kecamatan": "820610",
        "desa": "8206102004",
        "tps": "8206102004001",
        "url": "82\/8206\/820610\/8206102004\/8206102004001.json",
        "nama": "TPS 001, SOAGIMALAHA, KOTA MABA, HALMAHERA TIMUR, MALUKU UTARA"
    },
    {
        "provinsi": "82",
        "kabupaten": "8206",
        "kecamatan": "820610",
        "desa": "8206102004",
        "tps": "8206102004002",
        "url": "82\/8206\/820610\/8206102004\/8206102004002.json",
        "nama": "TPS 002, SOAGIMALAHA, KOTA MABA, HALMAHERA TIMUR, MALUKU UTARA"
    },
    {
        "provinsi": "82",
        "kabupaten": "8206",
        "kecamatan": "820610",
        "desa": "8206102004",
        "tps": "8206102004003",
        "url": "82\/8206\/820610\/8206102004\/8206102004003.json",
        "nama": "TPS 003, SOAGIMALAHA, KOTA MABA, HALMAHERA TIMUR, MALUKU UTARA"
    },
    {
        "provinsi": "82",
        "kabupaten": "8206",
        "kecamatan": "820610",
        "desa": "8206102004",
        "tps": "8206102004004",
        "url": "82\/8206\/820610\/8206102004\/8206102004004.json",
        "nama": "TPS 004, SOAGIMALAHA, KOTA MABA, HALMAHERA TIMUR, MALUKU UTARA"
    },
    {
        "provinsi": "82",
        "kabupaten": "8206",
        "kecamatan": "820610",
        "desa": "8206102004",
        "tps": "8206102004005",
        "url": "82\/8206\/820610\/8206102004\/8206102004005.json",
        "nama": "TPS 005, SOAGIMALAHA, KOTA MABA, HALMAHERA TIMUR, MALUKU UTARA"
    },
    {
        "provinsi": "82",
        "kabupaten": "8206",
        "kecamatan": "820610",
        "desa": "8206102004",
        "tps": "8206102004006",
        "url": "82\/8206\/820610\/8206102004\/8206102004006.json",
        "nama": "TPS 006, SOAGIMALAHA, KOTA MABA, HALMAHERA TIMUR, MALUKU UTARA"
    },
    {
        "provinsi": "82",
        "kabupaten": "8206",
        "kecamatan": "820610",
        "desa": "8206102004",
        "tps": "8206102004007",
        "url": "82\/8206\/820610\/8206102004\/8206102004007.json",
        "nama": "TPS 007, SOAGIMALAHA, KOTA MABA, HALMAHERA TIMUR, MALUKU UTARA"
    },
    {
        "provinsi": "82",
        "kabupaten": "8206",
        "kecamatan": "820610",
        "desa": "8206102004",
        "tps": "8206102004008",
        "url": "82\/8206\/820610\/8206102004\/8206102004008.json",
        "nama": "TPS 008, SOAGIMALAHA, KOTA MABA, HALMAHERA TIMUR, MALUKU UTARA"
    },
    {
        "provinsi": "82",
        "kabupaten": "8206",
        "kecamatan": "820610",
        "desa": "8206102004",
        "tps": "8206102004009",
        "url": "82\/8206\/820610\/8206102004\/8206102004009.json",
        "nama": "TPS 009, SOAGIMALAHA, KOTA MABA, HALMAHERA TIMUR, MALUKU UTARA"
    },
    {
        "provinsi": "82",
        "kabupaten": "8206",
        "kecamatan": "820610",
        "desa": "8206102004",
        "tps": "8206102004010",
        "url": "82\/8206\/820610\/8206102004\/8206102004010.json",
        "nama": "TPS 010, SOAGIMALAHA, KOTA MABA, HALMAHERA TIMUR, MALUKU UTARA"
    },
    {
        "provinsi": "82",
        "kabupaten": "8206",
        "kecamatan": "820610",
        "desa": "8206102002",
        "tps": "8206102002001",
        "url": "82\/8206\/820610\/8206102002\/8206102002001.json",
        "nama": "TPS 001, SOALAIPOH, KOTA MABA, HALMAHERA TIMUR, MALUKU UTARA"
    },
    {
        "provinsi": "82",
        "kabupaten": "8206",
        "kecamatan": "820610",
        "desa": "8206102002",
        "tps": "8206102002002",
        "url": "82\/8206\/820610\/8206102002\/8206102002002.json",
        "nama": "TPS 002, SOALAIPOH, KOTA MABA, HALMAHERA TIMUR, MALUKU UTARA"
    },
    {
        "provinsi": "82",
        "kabupaten": "8206",
        "kecamatan": "820610",
        "desa": "8206102002",
        "tps": "8206102002003",
        "url": "82\/8206\/820610\/8206102002\/8206102002003.json",
        "nama": "TPS 003, SOALAIPOH, KOTA MABA, HALMAHERA TIMUR, MALUKU UTARA"
    },
    {
        "provinsi": "82",
        "kabupaten": "8206",
        "kecamatan": "820610",
        "desa": "8206102003",
        "tps": "8206102003001",
        "url": "82\/8206\/820610\/8206102003\/8206102003001.json",
        "nama": "TPS 001, SOASANGAJI, KOTA MABA, HALMAHERA TIMUR, MALUKU UTARA"
    },
    {
        "provinsi": "82",
        "kabupaten": "8206",
        "kecamatan": "820610",
        "desa": "8206102003",
        "tps": "8206102003002",
        "url": "82\/8206\/820610\/8206102003\/8206102003002.json",
        "nama": "TPS 002, SOASANGAJI, KOTA MABA, HALMAHERA TIMUR, MALUKU UTARA"
    },
    {
        "provinsi": "82",
        "kabupaten": "8206",
        "kecamatan": "820610",
        "desa": "8206102003",
        "tps": "8206102003003",
        "url": "82\/8206\/820610\/8206102003\/8206102003003.json",
        "nama": "TPS 003, SOASANGAJI, KOTA MABA, HALMAHERA TIMUR, MALUKU UTARA"
    },
    {
        "provinsi": "82",
        "kabupaten": "8206",
        "kecamatan": "820610",
        "desa": "8206102006",
        "tps": "8206102006001",
        "url": "82\/8206\/820610\/8206102006\/8206102006001.json",
        "nama": "TPS 001, TEWIL, KOTA MABA, HALMAHERA TIMUR, MALUKU UTARA"
    },
    {
        "provinsi": "82",
        "kabupaten": "8206",
        "kecamatan": "820610",
        "desa": "8206102006",
        "tps": "8206102006002",
        "url": "82\/8206\/820610\/8206102006\/8206102006002.json",
        "nama": "TPS 002, TEWIL, KOTA MABA, HALMAHERA TIMUR, MALUKU UTARA"
    },
    {
        "provinsi": "82",
        "kabupaten": "8206",
        "kecamatan": "820610",
        "desa": "8206102001",
        "tps": "8206102001001",
        "url": "82\/8206\/820610\/8206102001\/8206102001001.json",
        "nama": "TPS 001, WAILUKUM, KOTA MABA, HALMAHERA TIMUR, MALUKU UTARA"
    },
    {
        "provinsi": "82",
        "kabupaten": "8206",
        "kecamatan": "820610",
        "desa": "8206102001",
        "tps": "8206102001002",
        "url": "82\/8206\/820610\/8206102001\/8206102001002.json",
        "nama": "TPS 002, WAILUKUM, KOTA MABA, HALMAHERA TIMUR, MALUKU UTARA"
    },
    {
        "provinsi": "82",
        "kabupaten": "8206",
        "kecamatan": "820610",
        "desa": "8206102001",
        "tps": "8206102001003",
        "url": "82\/8206\/820610\/8206102001\/8206102001003.json",
        "nama": "TPS 003, WAILUKUM, KOTA MABA, HALMAHERA TIMUR, MALUKU UTARA"
    },
    {
        "provinsi": "82",
        "kabupaten": "8206",
        "kecamatan": "820602",
        "desa": "8206022025",
        "tps": "8206022025001",
        "url": "82\/8206\/820602\/8206022025\/8206022025001.json",
        "nama": "TPS 001, BABURINO, MABA, HALMAHERA TIMUR, MALUKU UTARA"
    },
    {
        "provinsi": "82",
        "kabupaten": "8206",
        "kecamatan": "820602",
        "desa": "8206022025",
        "tps": "8206022025002",
        "url": "82\/8206\/820602\/8206022025\/8206022025002.json",
        "nama": "TPS 002, BABURINO, MABA, HALMAHERA TIMUR, MALUKU UTARA"
    },
    {
        "provinsi": "82",
        "kabupaten": "8206",
        "kecamatan": "820602",
        "desa": "8206022001",
        "tps": "8206022001001",
        "url": "82\/8206\/820602\/8206022001\/8206022001001.json",
        "nama": "TPS 001, BULI, MABA, HALMAHERA TIMUR, MALUKU UTARA"
    },
    {
        "provinsi": "82",
        "kabupaten": "8206",
        "kecamatan": "820602",
        "desa": "8206022001",
        "tps": "8206022001002",
        "url": "82\/8206\/820602\/8206022001\/8206022001002.json",
        "nama": "TPS 002, BULI, MABA, HALMAHERA TIMUR, MALUKU UTARA"
    },
    {
        "provinsi": "82",
        "kabupaten": "8206",
        "kecamatan": "820602",
        "desa": "8206022001",
        "tps": "8206022001003",
        "url": "82\/8206\/820602\/8206022001\/8206022001003.json",
        "nama": "TPS 003, BULI, MABA, HALMAHERA TIMUR, MALUKU UTARA"
    },
    {
        "provinsi": "82",
        "kabupaten": "8206",
        "kecamatan": "820602",
        "desa": "8206022001",
        "tps": "8206022001004",
        "url": "82\/8206\/820602\/8206022001\/8206022001004.json",
        "nama": "TPS 004, BULI, MABA, HALMAHERA TIMUR, MALUKU UTARA"
    },
    {
        "provinsi": "82",
        "kabupaten": "8206",
        "kecamatan": "820602",
        "desa": "8206022001",
        "tps": "8206022001005",
        "url": "82\/8206\/820602\/8206022001\/8206022001005.json",
        "nama": "TPS 005, BULI, MABA, HALMAHERA TIMUR, MALUKU UTARA"
    },
    {
        "provinsi": "82",
        "kabupaten": "8206",
        "kecamatan": "820602",
        "desa": "8206022001",
        "tps": "8206022001006",
        "url": "82\/8206\/820602\/8206022001\/8206022001006.json",
        "nama": "TPS 006, BULI, MABA, HALMAHERA TIMUR, MALUKU UTARA"
    },
    {
        "provinsi": "82",
        "kabupaten": "8206",
        "kecamatan": "820602",
        "desa": "8206022001",
        "tps": "8206022001007",
        "url": "82\/8206\/820602\/8206022001\/8206022001007.json",
        "nama": "TPS 007, BULI, MABA, HALMAHERA TIMUR, MALUKU UTARA"
    },
    {
        "provinsi": "82",
        "kabupaten": "8206",
        "kecamatan": "820602",
        "desa": "8206022002",
        "tps": "8206022002001",
        "url": "82\/8206\/820602\/8206022002\/8206022002001.json",
        "nama": "TPS 001, BULI ASAL, MABA, HALMAHERA TIMUR, MALUKU UTARA"
    },
    {
        "provinsi": "82",
        "kabupaten": "8206",
        "kecamatan": "820602",
        "desa": "8206022002",
        "tps": "8206022002002",
        "url": "82\/8206\/820602\/8206022002\/8206022002002.json",
        "nama": "TPS 002, BULI ASAL, MABA, HALMAHERA TIMUR, MALUKU UTARA"
    },
    {
        "provinsi": "82",
        "kabupaten": "8206",
        "kecamatan": "820602",
        "desa": "8206022002",
        "tps": "8206022002003",
        "url": "82\/8206\/820602\/8206022002\/8206022002003.json",
        "nama": "TPS 003, BULI ASAL, MABA, HALMAHERA TIMUR, MALUKU UTARA"
    },
    {
        "provinsi": "82",
        "kabupaten": "8206",
        "kecamatan": "820602",
        "desa": "8206022003",
        "tps": "8206022003001",
        "url": "82\/8206\/820602\/8206022003\/8206022003001.json",
        "nama": "TPS 001, BULI KARYA, MABA, HALMAHERA TIMUR, MALUKU UTARA"
    },
    {
        "provinsi": "82",
        "kabupaten": "8206",
        "kecamatan": "820602",
        "desa": "8206022003",
        "tps": "8206022003002",
        "url": "82\/8206\/820602\/8206022003\/8206022003002.json",
        "nama": "TPS 002, BULI KARYA, MABA, HALMAHERA TIMUR, MALUKU UTARA"
    },
    {
        "provinsi": "82",
        "kabupaten": "8206",
        "kecamatan": "820602",
        "desa": "8206022003",
        "tps": "8206022003003",
        "url": "82\/8206\/820602\/8206022003\/8206022003003.json",
        "nama": "TPS 003, BULI KARYA, MABA, HALMAHERA TIMUR, MALUKU UTARA"
    },
    {
        "provinsi": "82",
        "kabupaten": "8206",
        "kecamatan": "820602",
        "desa": "8206022003",
        "tps": "8206022003004",
        "url": "82\/8206\/820602\/8206022003\/8206022003004.json",
        "nama": "TPS 004, BULI KARYA, MABA, HALMAHERA TIMUR, MALUKU UTARA"
    },
    {
        "provinsi": "82",
        "kabupaten": "8206",
        "kecamatan": "820602",
        "desa": "8206022003",
        "tps": "8206022003005",
        "url": "82\/8206\/820602\/8206022003\/8206022003005.json",
        "nama": "TPS 005, BULI KARYA, MABA, HALMAHERA TIMUR, MALUKU UTARA"
    },
    {
        "provinsi": "82",
        "kabupaten": "8206",
        "kecamatan": "820602",
        "desa": "8206022024",
        "tps": "8206022024001",
        "url": "82\/8206\/820602\/8206022024\/8206022024001.json",
        "nama": "TPS 001, GAMESAN, MABA, HALMAHERA TIMUR, MALUKU UTARA"
    },
    {
        "provinsi": "82",
        "kabupaten": "8206",
        "kecamatan": "820602",
        "desa": "8206022024",
        "tps": "8206022024002",
        "url": "82\/8206\/820602\/8206022024\/8206022024002.json",
        "nama": "TPS 002, GAMESAN, MABA, HALMAHERA TIMUR, MALUKU UTARA"
    },
    {
        "provinsi": "82",
        "kabupaten": "8206",
        "kecamatan": "820602",
        "desa": "8206022013",
        "tps": "8206022013001",
        "url": "82\/8206\/820602\/8206022013\/8206022013001.json",
        "nama": "TPS 001, GELTOLI, MABA, HALMAHERA TIMUR, MALUKU UTARA"
    },
    {
        "provinsi": "82",
        "kabupaten": "8206",
        "kecamatan": "820602",
        "desa": "8206022013",
        "tps": "8206022013002",
        "url": "82\/8206\/820602\/8206022013\/8206022013002.json",
        "nama": "TPS 002, GELTOLI, MABA, HALMAHERA TIMUR, MALUKU UTARA"
    },
    {
        "provinsi": "82",
        "kabupaten": "8206",
        "kecamatan": "820602",
        "desa": "8206022013",
        "tps": "8206022013003",
        "url": "82\/8206\/820602\/8206022013\/8206022013003.json",
        "nama": "TPS 003, GELTOLI, MABA, HALMAHERA TIMUR, MALUKU UTARA"
    },
    {
        "provinsi": "82",
        "kabupaten": "8206",
        "kecamatan": "820602",
        "desa": "8206022013",
        "tps": "8206022013004",
        "url": "82\/8206\/820602\/8206022013\/8206022013004.json",
        "nama": "TPS 004, GELTOLI, MABA, HALMAHERA TIMUR, MALUKU UTARA"
    },
    {
        "provinsi": "82",
        "kabupaten": "8206",
        "kecamatan": "820602",
        "desa": "8206022013",
        "tps": "8206022013005",
        "url": "82\/8206\/820602\/8206022013\/8206022013005.json",
        "nama": "TPS 005, GELTOLI, MABA, HALMAHERA TIMUR, MALUKU UTARA"
    },
    {
        "provinsi": "82",
        "kabupaten": "8206",
        "kecamatan": "820602",
        "desa": "8206022013",
        "tps": "8206022013006",
        "url": "82\/8206\/820602\/8206022013\/8206022013006.json",
        "nama": "TPS 006, GELTOLI, MABA, HALMAHERA TIMUR, MALUKU UTARA"
    },
    {
        "provinsi": "82",
        "kabupaten": "8206",
        "kecamatan": "820602",
        "desa": "8206022014",
        "tps": "8206022014001",
        "url": "82\/8206\/820602\/8206022014\/8206022014001.json",
        "nama": "TPS 001, PEKAULANG, MABA, HALMAHERA TIMUR, MALUKU UTARA"
    },
    {
        "provinsi": "82",
        "kabupaten": "8206",
        "kecamatan": "820602",
        "desa": "8206022012",
        "tps": "8206022012001",
        "url": "82\/8206\/820602\/8206022012\/8206022012001.json",
        "nama": "TPS 001, SAILAL, MABA, HALMAHERA TIMUR, MALUKU UTARA"
    },
    {
        "provinsi": "82",
        "kabupaten": "8206",
        "kecamatan": "820602",
        "desa": "8206022012",
        "tps": "8206022012002",
        "url": "82\/8206\/820602\/8206022012\/8206022012002.json",
        "nama": "TPS 002, SAILAL, MABA, HALMAHERA TIMUR, MALUKU UTARA"
    },
    {
        "provinsi": "82",
        "kabupaten": "8206",
        "kecamatan": "820602",
        "desa": "8206022012",
        "tps": "8206022012003",
        "url": "82\/8206\/820602\/8206022012\/8206022012003.json",
        "nama": "TPS 003, SAILAL, MABA, HALMAHERA TIMUR, MALUKU UTARA"
    },
    {
        "provinsi": "82",
        "kabupaten": "8206",
        "kecamatan": "820602",
        "desa": "8206022012",
        "tps": "8206022012004",
        "url": "82\/8206\/820602\/8206022012\/8206022012004.json",
        "nama": "TPS 004, SAILAL, MABA, HALMAHERA TIMUR, MALUKU UTARA"
    },
    {
        "provinsi": "82",
        "kabupaten": "8206",
        "kecamatan": "820602",
        "desa": "8206022023",
        "tps": "8206022023001",
        "url": "82\/8206\/820602\/8206022023\/8206022023001.json",
        "nama": "TPS 001, TELUK BULI, MABA, HALMAHERA TIMUR, MALUKU UTARA"
    },
    {
        "provinsi": "82",
        "kabupaten": "8206",
        "kecamatan": "820602",
        "desa": "8206022023",
        "tps": "8206022023002",
        "url": "82\/8206\/820602\/8206022023\/8206022023002.json",
        "nama": "TPS 002, TELUK BULI, MABA, HALMAHERA TIMUR, MALUKU UTARA"
    },
    {
        "provinsi": "82",
        "kabupaten": "8206",
        "kecamatan": "820602",
        "desa": "8206022023",
        "tps": "8206022023003",
        "url": "82\/8206\/820602\/8206022023\/8206022023003.json",
        "nama": "TPS 003, TELUK BULI, MABA, HALMAHERA TIMUR, MALUKU UTARA"
    },
    {
        "provinsi": "82",
        "kabupaten": "8206",
        "kecamatan": "820602",
        "desa": "8206022011",
        "tps": "8206022011001",
        "url": "82\/8206\/820602\/8206022011\/8206022011001.json",
        "nama": "TPS 001, WAYAFLI, MABA, HALMAHERA TIMUR, MALUKU UTARA"
    },
    {
        "provinsi": "82",
        "kabupaten": "8206",
        "kecamatan": "820602",
        "desa": "8206022011",
        "tps": "8206022011002",
        "url": "82\/8206\/820602\/8206022011\/8206022011002.json",
        "nama": "TPS 002, WAYAFLI, MABA, HALMAHERA TIMUR, MALUKU UTARA"
    },
    {
        "provinsi": "82",
        "kabupaten": "8206",
        "kecamatan": "820602",
        "desa": "8206022011",
        "tps": "8206022011003",
        "url": "82\/8206\/820602\/8206022011\/8206022011003.json",
        "nama": "TPS 003, WAYAFLI, MABA, HALMAHERA TIMUR, MALUKU UTARA"
    },
    {
        "provinsi": "82",
        "kabupaten": "8206",
        "kecamatan": "820603",
        "desa": "8206032001",
        "tps": "8206032001001",
        "url": "82\/8206\/820603\/8206032001\/8206032001001.json",
        "nama": "TPS 001, BICOLI, MABA SELATAN, HALMAHERA TIMUR, MALUKU UTARA"
    },
    {
        "provinsi": "82",
        "kabupaten": "8206",
        "kecamatan": "820603",
        "desa": "8206032001",
        "tps": "8206032001002",
        "url": "82\/8206\/820603\/8206032001\/8206032001002.json",
        "nama": "TPS 002, BICOLI, MABA SELATAN, HALMAHERA TIMUR, MALUKU UTARA"
    },
    {
        "provinsi": "82",
        "kabupaten": "8206",
        "kecamatan": "820603",
        "desa": "8206032001",
        "tps": "8206032001003",
        "url": "82\/8206\/820603\/8206032001\/8206032001003.json",
        "nama": "TPS 003, BICOLI, MABA SELATAN, HALMAHERA TIMUR, MALUKU UTARA"
    },
    {
        "provinsi": "82",
        "kabupaten": "8206",
        "kecamatan": "820603",
        "desa": "8206032001",
        "tps": "8206032001004",
        "url": "82\/8206\/820603\/8206032001\/8206032001004.json",
        "nama": "TPS 004, BICOLI, MABA SELATAN, HALMAHERA TIMUR, MALUKU UTARA"
    },
    {
        "provinsi": "82",
        "kabupaten": "8206",
        "kecamatan": "820603",
        "desa": "8206032001",
        "tps": "8206032001005",
        "url": "82\/8206\/820603\/8206032001\/8206032001005.json",
        "nama": "TPS 005, BICOLI, MABA SELATAN, HALMAHERA TIMUR, MALUKU UTARA"
    },
    {
        "provinsi": "82",
        "kabupaten": "8206",
        "kecamatan": "820603",
        "desa": "8206032005",
        "tps": "8206032005001",
        "url": "82\/8206\/820603\/8206032005\/8206032005001.json",
        "nama": "TPS 001, GOTOWASI, MABA SELATAN, HALMAHERA TIMUR, MALUKU UTARA"
    },
    {
        "provinsi": "82",
        "kabupaten": "8206",
        "kecamatan": "820603",
        "desa": "8206032005",
        "tps": "8206032005002",
        "url": "82\/8206\/820603\/8206032005\/8206032005002.json",
        "nama": "TPS 002, GOTOWASI, MABA SELATAN, HALMAHERA TIMUR, MALUKU UTARA"
    },
    {
        "provinsi": "82",
        "kabupaten": "8206",
        "kecamatan": "820603",
        "desa": "8206032005",
        "tps": "8206032005003",
        "url": "82\/8206\/820603\/8206032005\/8206032005003.json",
        "nama": "TPS 003, GOTOWASI, MABA SELATAN, HALMAHERA TIMUR, MALUKU UTARA"
    },
    {
        "provinsi": "82",
        "kabupaten": "8206",
        "kecamatan": "820603",
        "desa": "8206032005",
        "tps": "8206032005004",
        "url": "82\/8206\/820603\/8206032005\/8206032005004.json",
        "nama": "TPS 004, GOTOWASI, MABA SELATAN, HALMAHERA TIMUR, MALUKU UTARA"
    },
    {
        "provinsi": "82",
        "kabupaten": "8206",
        "kecamatan": "820603",
        "desa": "8206032010",
        "tps": "8206032010001",
        "url": "82\/8206\/820603\/8206032010\/8206032010001.json",
        "nama": "TPS 001, KASUBA, MABA SELATAN, HALMAHERA TIMUR, MALUKU UTARA"
    },
    {
        "provinsi": "82",
        "kabupaten": "8206",
        "kecamatan": "820603",
        "desa": "8206032010",
        "tps": "8206032010002",
        "url": "82\/8206\/820603\/8206032010\/8206032010002.json",
        "nama": "TPS 002, KASUBA, MABA SELATAN, HALMAHERA TIMUR, MALUKU UTARA"
    },
    {
        "provinsi": "82",
        "kabupaten": "8206",
        "kecamatan": "820603",
        "desa": "8206032004",
        "tps": "8206032004001",
        "url": "82\/8206\/820603\/8206032004\/8206032004001.json",
        "nama": "TPS 001, LOLEOLAMO, MABA SELATAN, HALMAHERA TIMUR, MALUKU UTARA"
    },
    {
        "provinsi": "82",
        "kabupaten": "8206",
        "kecamatan": "820603",
        "desa": "8206032004",
        "tps": "8206032004002",
        "url": "82\/8206\/820603\/8206032004\/8206032004002.json",
        "nama": "TPS 002, LOLEOLAMO, MABA SELATAN, HALMAHERA TIMUR, MALUKU UTARA"
    },
    {
        "provinsi": "82",
        "kabupaten": "8206",
        "kecamatan": "820603",
        "desa": "8206032012",
        "tps": "8206032012001",
        "url": "82\/8206\/820603\/8206032012\/8206032012001.json",
        "nama": "TPS 001, MOMOLE, MABA SELATAN, HALMAHERA TIMUR, MALUKU UTARA"
    },
    {
        "provinsi": "82",
        "kabupaten": "8206",
        "kecamatan": "820603",
        "desa": "8206032012",
        "tps": "8206032012002",
        "url": "82\/8206\/820603\/8206032012\/8206032012002.json",
        "nama": "TPS 002, MOMOLE, MABA SELATAN, HALMAHERA TIMUR, MALUKU UTARA"
    },
    {
        "provinsi": "82",
        "kabupaten": "8206",
        "kecamatan": "820603",
        "desa": "8206032012",
        "tps": "8206032012003",
        "url": "82\/8206\/820603\/8206032012\/8206032012003.json",
        "nama": "TPS 003, MOMOLE, MABA SELATAN, HALMAHERA TIMUR, MALUKU UTARA"
    },
    {
        "provinsi": "82",
        "kabupaten": "8206",
        "kecamatan": "820603",
        "desa": "8206032003",
        "tps": "8206032003001",
        "url": "82\/8206\/820603\/8206032003\/8206032003001.json",
        "nama": "TPS 001, PETELEY, MABA SELATAN, HALMAHERA TIMUR, MALUKU UTARA"
    },
    {
        "provinsi": "82",
        "kabupaten": "8206",
        "kecamatan": "820603",
        "desa": "8206032003",
        "tps": "8206032003002",
        "url": "82\/8206\/820603\/8206032003\/8206032003002.json",
        "nama": "TPS 002, PETELEY, MABA SELATAN, HALMAHERA TIMUR, MALUKU UTARA"
    },
    {
        "provinsi": "82",
        "kabupaten": "8206",
        "kecamatan": "820603",
        "desa": "8206032003",
        "tps": "8206032003003",
        "url": "82\/8206\/820603\/8206032003\/8206032003003.json",
        "nama": "TPS 003, PETELEY, MABA SELATAN, HALMAHERA TIMUR, MALUKU UTARA"
    },
    {
        "provinsi": "82",
        "kabupaten": "8206",
        "kecamatan": "820603",
        "desa": "8206032013",
        "tps": "8206032013001",
        "url": "82\/8206\/820603\/8206032013\/8206032013001.json",
        "nama": "TPS 001, SIL, MABA SELATAN, HALMAHERA TIMUR, MALUKU UTARA"
    },
    {
        "provinsi": "82",
        "kabupaten": "8206",
        "kecamatan": "820603",
        "desa": "8206032013",
        "tps": "8206032013002",
        "url": "82\/8206\/820603\/8206032013\/8206032013002.json",
        "nama": "TPS 002, SIL, MABA SELATAN, HALMAHERA TIMUR, MALUKU UTARA"
    },
    {
        "provinsi": "82",
        "kabupaten": "8206",
        "kecamatan": "820603",
        "desa": "8206032014",
        "tps": "8206032014001",
        "url": "82\/8206\/820603\/8206032014\/8206032014001.json",
        "nama": "TPS 001, SOWOLI, MABA SELATAN, HALMAHERA TIMUR, MALUKU UTARA"
    },
    {
        "provinsi": "82",
        "kabupaten": "8206",
        "kecamatan": "820603",
        "desa": "8206032002",
        "tps": "8206032002001",
        "url": "82\/8206\/820603\/8206032002\/8206032002001.json",
        "nama": "TPS 001, WACI, MABA SELATAN, HALMAHERA TIMUR, MALUKU UTARA"
    },
    {
        "provinsi": "82",
        "kabupaten": "8206",
        "kecamatan": "820603",
        "desa": "8206032002",
        "tps": "8206032002002",
        "url": "82\/8206\/820603\/8206032002\/8206032002002.json",
        "nama": "TPS 002, WACI, MABA SELATAN, HALMAHERA TIMUR, MALUKU UTARA"
    },
    {
        "provinsi": "82",
        "kabupaten": "8206",
        "kecamatan": "820603",
        "desa": "8206032002",
        "tps": "8206032002003",
        "url": "82\/8206\/820603\/8206032002\/8206032002003.json",
        "nama": "TPS 003, WACI, MABA SELATAN, HALMAHERA TIMUR, MALUKU UTARA"
    },
    {
        "provinsi": "82",
        "kabupaten": "8206",
        "kecamatan": "820608",
        "desa": "8206082011",
        "tps": "8206082011001",
        "url": "82\/8206\/820608\/8206082011\/8206082011001.json",
        "nama": "TPS 001, BABASARAM, MABA TENGAH, HALMAHERA TIMUR, MALUKU UTARA"
    },
    {
        "provinsi": "82",
        "kabupaten": "8206",
        "kecamatan": "820608",
        "desa": "8206082011",
        "tps": "8206082011002",
        "url": "82\/8206\/820608\/8206082011\/8206082011002.json",
        "nama": "TPS 002, BABASARAM, MABA TENGAH, HALMAHERA TIMUR, MALUKU UTARA"
    },
    {
        "provinsi": "82",
        "kabupaten": "8206",
        "kecamatan": "820608",
        "desa": "8206082004",
        "tps": "8206082004001",
        "url": "82\/8206\/820608\/8206082004\/8206082004001.json",
        "nama": "TPS 001, BANGUL, MABA TENGAH, HALMAHERA TIMUR, MALUKU UTARA"
    },
    {
        "provinsi": "82",
        "kabupaten": "8206",
        "kecamatan": "820608",
        "desa": "8206082008",
        "tps": "8206082008001",
        "url": "82\/8206\/820608\/8206082008\/8206082008001.json",
        "nama": "TPS 001, BEBSILI, MABA TENGAH, HALMAHERA TIMUR, MALUKU UTARA"
    },
    {
        "provinsi": "82",
        "kabupaten": "8206",
        "kecamatan": "820608",
        "desa": "8206082002",
        "tps": "8206082002001",
        "url": "82\/8206\/820608\/8206082002\/8206082002001.json",
        "nama": "TPS 001, BERINGIN LAMO, MABA TENGAH, HALMAHERA TIMUR, MALUKU UTARA"
    },
    {
        "provinsi": "82",
        "kabupaten": "8206",
        "kecamatan": "820608",
        "desa": "8206082002",
        "tps": "8206082002002",
        "url": "82\/8206\/820608\/8206082002\/8206082002002.json",
        "nama": "TPS 002, BERINGIN LAMO, MABA TENGAH, HALMAHERA TIMUR, MALUKU UTARA"
    },
    {
        "provinsi": "82",
        "kabupaten": "8206",
        "kecamatan": "820608",
        "desa": "8206082006",
        "tps": "8206082006001",
        "url": "82\/8206\/820608\/8206082006\/8206082006001.json",
        "nama": "TPS 001, DOROLAMO, MABA TENGAH, HALMAHERA TIMUR, MALUKU UTARA"
    },
    {
        "provinsi": "82",
        "kabupaten": "8206",
        "kecamatan": "820608",
        "desa": "8206082010",
        "tps": "8206082010001",
        "url": "82\/8206\/820608\/8206082010\/8206082010001.json",
        "nama": "TPS 001, GAIFOLI, MABA TENGAH, HALMAHERA TIMUR, MALUKU UTARA"
    },
    {
        "provinsi": "82",
        "kabupaten": "8206",
        "kecamatan": "820608",
        "desa": "8206082005",
        "tps": "8206082005001",
        "url": "82\/8206\/820608\/8206082005\/8206082005001.json",
        "nama": "TPS 001, MARASIPNO, MABA TENGAH, HALMAHERA TIMUR, MALUKU UTARA"
    },
    {
        "provinsi": "82",
        "kabupaten": "8206",
        "kecamatan": "820608",
        "desa": "8206082007",
        "tps": "8206082007001",
        "url": "82\/8206\/820608\/8206082007\/8206082007001.json",
        "nama": "TPS 001, MARATANA JAYA, MABA TENGAH, HALMAHERA TIMUR, MALUKU UTARA"
    },
    {
        "provinsi": "82",
        "kabupaten": "8206",
        "kecamatan": "820608",
        "desa": "8206082007",
        "tps": "8206082007002",
        "url": "82\/8206\/820608\/8206082007\/8206082007002.json",
        "nama": "TPS 002, MARATANA JAYA, MABA TENGAH, HALMAHERA TIMUR, MALUKU UTARA"
    },
    {
        "provinsi": "82",
        "kabupaten": "8206",
        "kecamatan": "820608",
        "desa": "8206082007",
        "tps": "8206082007003",
        "url": "82\/8206\/820608\/8206082007\/8206082007003.json",
        "nama": "TPS 003, MARATANA JAYA, MABA TENGAH, HALMAHERA TIMUR, MALUKU UTARA"
    },
    {
        "provinsi": "82",
        "kabupaten": "8206",
        "kecamatan": "820608",
        "desa": "8206082003",
        "tps": "8206082003001",
        "url": "82\/8206\/820608\/8206082003\/8206082003001.json",
        "nama": "TPS 001, MIAF, MABA TENGAH, HALMAHERA TIMUR, MALUKU UTARA"
    },
    {
        "provinsi": "82",
        "kabupaten": "8206",
        "kecamatan": "820608",
        "desa": "8206082003",
        "tps": "8206082003002",
        "url": "82\/8206\/820608\/8206082003\/8206082003002.json",
        "nama": "TPS 002, MIAF, MABA TENGAH, HALMAHERA TIMUR, MALUKU UTARA"
    },
    {
        "provinsi": "82",
        "kabupaten": "8206",
        "kecamatan": "820608",
        "desa": "8206082012",
        "tps": "8206082012001",
        "url": "82\/8206\/820608\/8206082012\/8206082012001.json",
        "nama": "TPS 001, TATANGAPU, MABA TENGAH, HALMAHERA TIMUR, MALUKU UTARA"
    },
    {
        "provinsi": "82",
        "kabupaten": "8206",
        "kecamatan": "820608",
        "desa": "8206082001",
        "tps": "8206082001001",
        "url": "82\/8206\/820608\/8206082001\/8206082001001.json",
        "nama": "TPS 001, WAYAMLI, MABA TENGAH, HALMAHERA TIMUR, MALUKU UTARA"
    },
    {
        "provinsi": "82",
        "kabupaten": "8206",
        "kecamatan": "820608",
        "desa": "8206082001",
        "tps": "8206082001002",
        "url": "82\/8206\/820608\/8206082001\/8206082001002.json",
        "nama": "TPS 002, WAYAMLI, MABA TENGAH, HALMAHERA TIMUR, MALUKU UTARA"
    },
    {
        "provinsi": "82",
        "kabupaten": "8206",
        "kecamatan": "820608",
        "desa": "8206082009",
        "tps": "8206082009001",
        "url": "82\/8206\/820608\/8206082009\/8206082009001.json",
        "nama": "TPS 001, YAWANLI, MABA TENGAH, HALMAHERA TIMUR, MALUKU UTARA"
    },
    {
        "provinsi": "82",
        "kabupaten": "8206",
        "kecamatan": "820608",
        "desa": "8206082009",
        "tps": "8206082009002",
        "url": "82\/8206\/820608\/8206082009\/8206082009002.json",
        "nama": "TPS 002, YAWANLI, MABA TENGAH, HALMAHERA TIMUR, MALUKU UTARA"
    },
    {
        "provinsi": "82",
        "kabupaten": "8206",
        "kecamatan": "820608",
        "desa": "8206082009",
        "tps": "8206082009003",
        "url": "82\/8206\/820608\/8206082009\/8206082009003.json",
        "nama": "TPS 003, YAWANLI, MABA TENGAH, HALMAHERA TIMUR, MALUKU UTARA"
    },
    {
        "provinsi": "82",
        "kabupaten": "8206",
        "kecamatan": "820609",
        "desa": "8206092008",
        "tps": "8206092008001",
        "url": "82\/8206\/820609\/8206092008\/8206092008001.json",
        "nama": "TPS 001, DOROMOI, MABA UTARA, HALMAHERA TIMUR, MALUKU UTARA"
    },
    {
        "provinsi": "82",
        "kabupaten": "8206",
        "kecamatan": "820609",
        "desa": "8206092008",
        "tps": "8206092008002",
        "url": "82\/8206\/820609\/8206092008\/8206092008002.json",
        "nama": "TPS 002, DOROMOI, MABA UTARA, HALMAHERA TIMUR, MALUKU UTARA"
    },
    {
        "provinsi": "82",
        "kabupaten": "8206",
        "kecamatan": "820609",
        "desa": "8206092002",
        "tps": "8206092002001",
        "url": "82\/8206\/820609\/8206092002\/8206092002001.json",
        "nama": "TPS 001, DOROSAGO, MABA UTARA, HALMAHERA TIMUR, MALUKU UTARA"
    },
    {
        "provinsi": "82",
        "kabupaten": "8206",
        "kecamatan": "820609",
        "desa": "8206092002",
        "tps": "8206092002002",
        "url": "82\/8206\/820609\/8206092002\/8206092002002.json",
        "nama": "TPS 002, DOROSAGO, MABA UTARA, HALMAHERA TIMUR, MALUKU UTARA"
    },
    {
        "provinsi": "82",
        "kabupaten": "8206",
        "kecamatan": "820609",
        "desa": "8206092002",
        "tps": "8206092002003",
        "url": "82\/8206\/820609\/8206092002\/8206092002003.json",
        "nama": "TPS 003, DOROSAGO, MABA UTARA, HALMAHERA TIMUR, MALUKU UTARA"
    },
    {
        "provinsi": "82",
        "kabupaten": "8206",
        "kecamatan": "820609",
        "desa": "8206092007",
        "tps": "8206092007001",
        "url": "82\/8206\/820609\/8206092007\/8206092007001.json",
        "nama": "TPS 001, JARA-JARA, MABA UTARA, HALMAHERA TIMUR, MALUKU UTARA"
    },
    {
        "provinsi": "82",
        "kabupaten": "8206",
        "kecamatan": "820609",
        "desa": "8206092007",
        "tps": "8206092007002",
        "url": "82\/8206\/820609\/8206092007\/8206092007002.json",
        "nama": "TPS 002, JARA-JARA, MABA UTARA, HALMAHERA TIMUR, MALUKU UTARA"
    },
    {
        "provinsi": "82",
        "kabupaten": "8206",
        "kecamatan": "820609",
        "desa": "8206092007",
        "tps": "8206092007003",
        "url": "82\/8206\/820609\/8206092007\/8206092007003.json",
        "nama": "TPS 003, JARA-JARA, MABA UTARA, HALMAHERA TIMUR, MALUKU UTARA"
    },
    {
        "provinsi": "82",
        "kabupaten": "8206",
        "kecamatan": "820609",
        "desa": "8206092009",
        "tps": "8206092009001",
        "url": "82\/8206\/820609\/8206092009\/8206092009001.json",
        "nama": "TPS 001, LILI, MABA UTARA, HALMAHERA TIMUR, MALUKU UTARA"
    },
    {
        "provinsi": "82",
        "kabupaten": "8206",
        "kecamatan": "820609",
        "desa": "8206092009",
        "tps": "8206092009002",
        "url": "82\/8206\/820609\/8206092009\/8206092009002.json",
        "nama": "TPS 002, LILI, MABA UTARA, HALMAHERA TIMUR, MALUKU UTARA"
    },
    {
        "provinsi": "82",
        "kabupaten": "8206",
        "kecamatan": "820609",
        "desa": "8206092004",
        "tps": "8206092004001",
        "url": "82\/8206\/820609\/8206092004\/8206092004001.json",
        "nama": "TPS 001, LOLASITA, MABA UTARA, HALMAHERA TIMUR, MALUKU UTARA"
    },
    {
        "provinsi": "82",
        "kabupaten": "8206",
        "kecamatan": "820609",
        "desa": "8206092004",
        "tps": "8206092004002",
        "url": "82\/8206\/820609\/8206092004\/8206092004002.json",
        "nama": "TPS 002, LOLASITA, MABA UTARA, HALMAHERA TIMUR, MALUKU UTARA"
    },
    {
        "provinsi": "82",
        "kabupaten": "8206",
        "kecamatan": "820609",
        "desa": "8206092004",
        "tps": "8206092004003",
        "url": "82\/8206\/820609\/8206092004\/8206092004003.json",
        "nama": "TPS 003, LOLASITA, MABA UTARA, HALMAHERA TIMUR, MALUKU UTARA"
    },
    {
        "provinsi": "82",
        "kabupaten": "8206",
        "kecamatan": "820609",
        "desa": "8206092003",
        "tps": "8206092003001",
        "url": "82\/8206\/820609\/8206092003\/8206092003001.json",
        "nama": "TPS 001, PATLEAN, MABA UTARA, HALMAHERA TIMUR, MALUKU UTARA"
    },
    {
        "provinsi": "82",
        "kabupaten": "8206",
        "kecamatan": "820609",
        "desa": "8206092003",
        "tps": "8206092003002",
        "url": "82\/8206\/820609\/8206092003\/8206092003002.json",
        "nama": "TPS 002, PATLEAN, MABA UTARA, HALMAHERA TIMUR, MALUKU UTARA"
    },
    {
        "provinsi": "82",
        "kabupaten": "8206",
        "kecamatan": "820609",
        "desa": "8206092003",
        "tps": "8206092003003",
        "url": "82\/8206\/820609\/8206092003\/8206092003003.json",
        "nama": "TPS 003, PATLEAN, MABA UTARA, HALMAHERA TIMUR, MALUKU UTARA"
    },
    {
        "provinsi": "82",
        "kabupaten": "8206",
        "kecamatan": "820609",
        "desa": "8206092003",
        "tps": "8206092003004",
        "url": "82\/8206\/820609\/8206092003\/8206092003004.json",
        "nama": "TPS 004, PATLEAN, MABA UTARA, HALMAHERA TIMUR, MALUKU UTARA"
    },
    {
        "provinsi": "82",
        "kabupaten": "8206",
        "kecamatan": "820609",
        "desa": "8206092010",
        "tps": "8206092010001",
        "url": "82\/8206\/820609\/8206092010\/8206092010001.json",
        "nama": "TPS 001, PATLEAN JAYA, MABA UTARA, HALMAHERA TIMUR, MALUKU UTARA"
    },
    {
        "provinsi": "82",
        "kabupaten": "8206",
        "kecamatan": "820609",
        "desa": "8206092010",
        "tps": "8206092010002",
        "url": "82\/8206\/820609\/8206092010\/8206092010002.json",
        "nama": "TPS 002, PATLEAN JAYA, MABA UTARA, HALMAHERA TIMUR, MALUKU UTARA"
    },
    {
        "provinsi": "82",
        "kabupaten": "8206",
        "kecamatan": "820609",
        "desa": "8206092006",
        "tps": "8206092006001",
        "url": "82\/8206\/820609\/8206092006\/8206092006001.json",
        "nama": "TPS 001, PUMLANGA, MABA UTARA, HALMAHERA TIMUR, MALUKU UTARA"
    },
    {
        "provinsi": "82",
        "kabupaten": "8206",
        "kecamatan": "820609",
        "desa": "8206092006",
        "tps": "8206092006002",
        "url": "82\/8206\/820609\/8206092006\/8206092006002.json",
        "nama": "TPS 002, PUMLANGA, MABA UTARA, HALMAHERA TIMUR, MALUKU UTARA"
    },
    {
        "provinsi": "82",
        "kabupaten": "8206",
        "kecamatan": "820609",
        "desa": "8206092006",
        "tps": "8206092006003",
        "url": "82\/8206\/820609\/8206092006\/8206092006003.json",
        "nama": "TPS 003, PUMLANGA, MABA UTARA, HALMAHERA TIMUR, MALUKU UTARA"
    },
    {
        "provinsi": "82",
        "kabupaten": "8206",
        "kecamatan": "820609",
        "desa": "8206092001",
        "tps": "8206092001001",
        "url": "82\/8206\/820609\/8206092001\/8206092001001.json",
        "nama": "TPS 001, SOSOLAT, MABA UTARA, HALMAHERA TIMUR, MALUKU UTARA"
    },
    {
        "provinsi": "82",
        "kabupaten": "8206",
        "kecamatan": "820609",
        "desa": "8206092001",
        "tps": "8206092001002",
        "url": "82\/8206\/820609\/8206092001\/8206092001002.json",
        "nama": "TPS 002, SOSOLAT, MABA UTARA, HALMAHERA TIMUR, MALUKU UTARA"
    },
    {
        "provinsi": "82",
        "kabupaten": "8206",
        "kecamatan": "820609",
        "desa": "8206092001",
        "tps": "8206092001003",
        "url": "82\/8206\/820609\/8206092001\/8206092001003.json",
        "nama": "TPS 003, SOSOLAT, MABA UTARA, HALMAHERA TIMUR, MALUKU UTARA"
    },
    {
        "provinsi": "82",
        "kabupaten": "8206",
        "kecamatan": "820609",
        "desa": "8206092005",
        "tps": "8206092005001",
        "url": "82\/8206\/820609\/8206092005\/8206092005001.json",
        "nama": "TPS 001, WASILEO, MABA UTARA, HALMAHERA TIMUR, MALUKU UTARA"
    },
    {
        "provinsi": "82",
        "kabupaten": "8206",
        "kecamatan": "820609",
        "desa": "8206092005",
        "tps": "8206092005002",
        "url": "82\/8206\/820609\/8206092005\/8206092005002.json",
        "nama": "TPS 002, WASILEO, MABA UTARA, HALMAHERA TIMUR, MALUKU UTARA"
    },
    {
        "provinsi": "82",
        "kabupaten": "8206",
        "kecamatan": "820609",
        "desa": "8206092005",
        "tps": "8206092005003",
        "url": "82\/8206\/820609\/8206092005\/8206092005003.json",
        "nama": "TPS 003, WASILEO, MABA UTARA, HALMAHERA TIMUR, MALUKU UTARA"
    },
    {
        "provinsi": "82",
        "kabupaten": "8206",
        "kecamatan": "820609",
        "desa": "8206092005",
        "tps": "8206092005004",
        "url": "82\/8206\/820609\/8206092005\/8206092005004.json",
        "nama": "TPS 004, WASILEO, MABA UTARA, HALMAHERA TIMUR, MALUKU UTARA"
    },
    {
        "provinsi": "82",
        "kabupaten": "8206",
        "kecamatan": "820601",
        "desa": "8206012014",
        "tps": "8206012014001",
        "url": "82\/8206\/820601\/8206012014\/8206012014001.json",
        "nama": "TPS 001, BATU RAJA, WASILE, HALMAHERA TIMUR, MALUKU UTARA"
    },
    {
        "provinsi": "82",
        "kabupaten": "8206",
        "kecamatan": "820601",
        "desa": "8206012014",
        "tps": "8206012014002",
        "url": "82\/8206\/820601\/8206012014\/8206012014002.json",
        "nama": "TPS 002, BATU RAJA, WASILE, HALMAHERA TIMUR, MALUKU UTARA"
    },
    {
        "provinsi": "82",
        "kabupaten": "8206",
        "kecamatan": "820601",
        "desa": "8206012014",
        "tps": "8206012014003",
        "url": "82\/8206\/820601\/8206012014\/8206012014003.json",
        "nama": "TPS 003, BATU RAJA, WASILE, HALMAHERA TIMUR, MALUKU UTARA"
    },
    {
        "provinsi": "82",
        "kabupaten": "8206",
        "kecamatan": "820601",
        "desa": "8206012014",
        "tps": "8206012014004",
        "url": "82\/8206\/820601\/8206012014\/8206012014004.json",
        "nama": "TPS 004, BATU RAJA, WASILE, HALMAHERA TIMUR, MALUKU UTARA"
    },
    {
        "provinsi": "82",
        "kabupaten": "8206",
        "kecamatan": "820601",
        "desa": "8206012014",
        "tps": "8206012014005",
        "url": "82\/8206\/820601\/8206012014\/8206012014005.json",
        "nama": "TPS 005, BATU RAJA, WASILE, HALMAHERA TIMUR, MALUKU UTARA"
    },
    {
        "provinsi": "82",
        "kabupaten": "8206",
        "kecamatan": "820601",
        "desa": "8206012014",
        "tps": "8206012014006",
        "url": "82\/8206\/820601\/8206012014\/8206012014006.json",
        "nama": "TPS 006, BATU RAJA, WASILE, HALMAHERA TIMUR, MALUKU UTARA"
    },
    {
        "provinsi": "82",
        "kabupaten": "8206",
        "kecamatan": "820601",
        "desa": "8206012014",
        "tps": "8206012014007",
        "url": "82\/8206\/820601\/8206012014\/8206012014007.json",
        "nama": "TPS 007, BATU RAJA, WASILE, HALMAHERA TIMUR, MALUKU UTARA"
    },
    {
        "provinsi": "82",
        "kabupaten": "8206",
        "kecamatan": "820601",
        "desa": "8206012009",
        "tps": "8206012009001",
        "url": "82\/8206\/820601\/8206012009\/8206012009001.json",
        "nama": "TPS 001, BUMI RESTU, WASILE, HALMAHERA TIMUR, MALUKU UTARA"
    },
    {
        "provinsi": "82",
        "kabupaten": "8206",
        "kecamatan": "820601",
        "desa": "8206012009",
        "tps": "8206012009002",
        "url": "82\/8206\/820601\/8206012009\/8206012009002.json",
        "nama": "TPS 002, BUMI RESTU, WASILE, HALMAHERA TIMUR, MALUKU UTARA"
    },
    {
        "provinsi": "82",
        "kabupaten": "8206",
        "kecamatan": "820601",
        "desa": "8206012009",
        "tps": "8206012009003",
        "url": "82\/8206\/820601\/8206012009\/8206012009003.json",
        "nama": "TPS 003, BUMI RESTU, WASILE, HALMAHERA TIMUR, MALUKU UTARA"
    },
    {
        "provinsi": "82",
        "kabupaten": "8206",
        "kecamatan": "820601",
        "desa": "8206012009",
        "tps": "8206012009004",
        "url": "82\/8206\/820601\/8206012009\/8206012009004.json",
        "nama": "TPS 004, BUMI RESTU, WASILE, HALMAHERA TIMUR, MALUKU UTARA"
    },
    {
        "provinsi": "82",
        "kabupaten": "8206",
        "kecamatan": "820601",
        "desa": "8206012009",
        "tps": "8206012009005",
        "url": "82\/8206\/820601\/8206012009\/8206012009005.json",
        "nama": "TPS 005, BUMI RESTU, WASILE, HALMAHERA TIMUR, MALUKU UTARA"
    },
    {
        "provinsi": "82",
        "kabupaten": "8206",
        "kecamatan": "820601",
        "desa": "8206012009",
        "tps": "8206012009006",
        "url": "82\/8206\/820601\/8206012009\/8206012009006.json",
        "nama": "TPS 006, BUMI RESTU, WASILE, HALMAHERA TIMUR, MALUKU UTARA"
    },
    {
        "provinsi": "82",
        "kabupaten": "8206",
        "kecamatan": "820601",
        "desa": "8206012009",
        "tps": "8206012009007",
        "url": "82\/8206\/820601\/8206012009\/8206012009007.json",
        "nama": "TPS 007, BUMI RESTU, WASILE, HALMAHERA TIMUR, MALUKU UTARA"
    },
    {
        "provinsi": "82",
        "kabupaten": "8206",
        "kecamatan": "820601",
        "desa": "8206012009",
        "tps": "8206012009008",
        "url": "82\/8206\/820601\/8206012009\/8206012009008.json",
        "nama": "TPS 008, BUMI RESTU, WASILE, HALMAHERA TIMUR, MALUKU UTARA"
    },
    {
        "provinsi": "82",
        "kabupaten": "8206",
        "kecamatan": "820601",
        "desa": "8206012008",
        "tps": "8206012008001",
        "url": "82\/8206\/820601\/8206012008\/8206012008001.json",
        "nama": "TPS 001, CEMARA JAYA, WASILE, HALMAHERA TIMUR, MALUKU UTARA"
    },
    {
        "provinsi": "82",
        "kabupaten": "8206",
        "kecamatan": "820601",
        "desa": "8206012008",
        "tps": "8206012008002",
        "url": "82\/8206\/820601\/8206012008\/8206012008002.json",
        "nama": "TPS 002, CEMARA JAYA, WASILE, HALMAHERA TIMUR, MALUKU UTARA"
    },
    {
        "provinsi": "82",
        "kabupaten": "8206",
        "kecamatan": "820601",
        "desa": "8206012008",
        "tps": "8206012008003",
        "url": "82\/8206\/820601\/8206012008\/8206012008003.json",
        "nama": "TPS 003, CEMARA JAYA, WASILE, HALMAHERA TIMUR, MALUKU UTARA"
    },
    {
        "provinsi": "82",
        "kabupaten": "8206",
        "kecamatan": "820601",
        "desa": "8206012008",
        "tps": "8206012008004",
        "url": "82\/8206\/820601\/8206012008\/8206012008004.json",
        "nama": "TPS 004, CEMARA JAYA, WASILE, HALMAHERA TIMUR, MALUKU UTARA"
    },
    {
        "provinsi": "82",
        "kabupaten": "8206",
        "kecamatan": "820601",
        "desa": "8206012008",
        "tps": "8206012008005",
        "url": "82\/8206\/820601\/8206012008\/8206012008005.json",
        "nama": "TPS 005, CEMARA JAYA, WASILE, HALMAHERA TIMUR, MALUKU UTARA"
    },
    {
        "provinsi": "82",
        "kabupaten": "8206",
        "kecamatan": "820601",
        "desa": "8206012008",
        "tps": "8206012008006",
        "url": "82\/8206\/820601\/8206012008\/8206012008006.json",
        "nama": "TPS 006, CEMARA JAYA, WASILE, HALMAHERA TIMUR, MALUKU UTARA"
    },
    {
        "provinsi": "82",
        "kabupaten": "8206",
        "kecamatan": "820601",
        "desa": "8206012016",
        "tps": "8206012016001",
        "url": "82\/8206\/820601\/8206012016\/8206012016001.json",
        "nama": "TPS 001, GULAPAPO, WASILE, HALMAHERA TIMUR, MALUKU UTARA"
    },
    {
        "provinsi": "82",
        "kabupaten": "8206",
        "kecamatan": "820601",
        "desa": "8206012016",
        "tps": "8206012016002",
        "url": "82\/8206\/820601\/8206012016\/8206012016002.json",
        "nama": "TPS 002, GULAPAPO, WASILE, HALMAHERA TIMUR, MALUKU UTARA"
    },
    {
        "provinsi": "82",
        "kabupaten": "8206",
        "kecamatan": "820601",
        "desa": "8206012015",
        "tps": "8206012015001",
        "url": "82\/8206\/820601\/8206012015\/8206012015001.json",
        "nama": "TPS 001, MEKAR SARI, WASILE, HALMAHERA TIMUR, MALUKU UTARA"
    },
    {
        "provinsi": "82",
        "kabupaten": "8206",
        "kecamatan": "820601",
        "desa": "8206012015",
        "tps": "8206012015002",
        "url": "82\/8206\/820601\/8206012015\/8206012015002.json",
        "nama": "TPS 002, MEKAR SARI, WASILE, HALMAHERA TIMUR, MALUKU UTARA"
    },
    {
        "provinsi": "82",
        "kabupaten": "8206",
        "kecamatan": "820601",
        "desa": "8206012015",
        "tps": "8206012015003",
        "url": "82\/8206\/820601\/8206012015\/8206012015003.json",
        "nama": "TPS 003, MEKAR SARI, WASILE, HALMAHERA TIMUR, MALUKU UTARA"
    },
    {
        "provinsi": "82",
        "kabupaten": "8206",
        "kecamatan": "820601",
        "desa": "8206012015",
        "tps": "8206012015004",
        "url": "82\/8206\/820601\/8206012015\/8206012015004.json",
        "nama": "TPS 004, MEKAR SARI, WASILE, HALMAHERA TIMUR, MALUKU UTARA"
    },
    {
        "provinsi": "82",
        "kabupaten": "8206",
        "kecamatan": "820601",
        "desa": "8206012015",
        "tps": "8206012015005",
        "url": "82\/8206\/820601\/8206012015\/8206012015005.json",
        "nama": "TPS 005, MEKAR SARI, WASILE, HALMAHERA TIMUR, MALUKU UTARA"
    },
    {
        "provinsi": "82",
        "kabupaten": "8206",
        "kecamatan": "820601",
        "desa": "8206012015",
        "tps": "8206012015006",
        "url": "82\/8206\/820601\/8206012015\/8206012015006.json",
        "nama": "TPS 006, MEKAR SARI, WASILE, HALMAHERA TIMUR, MALUKU UTARA"
    },
    {
        "provinsi": "82",
        "kabupaten": "8206",
        "kecamatan": "820601",
        "desa": "8206012006",
        "tps": "8206012006001",
        "url": "82\/8206\/820601\/8206012006\/8206012006001.json",
        "nama": "TPS 001, SUBAIM, WASILE, HALMAHERA TIMUR, MALUKU UTARA"
    },
    {
        "provinsi": "82",
        "kabupaten": "8206",
        "kecamatan": "820601",
        "desa": "8206012006",
        "tps": "8206012006002",
        "url": "82\/8206\/820601\/8206012006\/8206012006002.json",
        "nama": "TPS 002, SUBAIM, WASILE, HALMAHERA TIMUR, MALUKU UTARA"
    },
    {
        "provinsi": "82",
        "kabupaten": "8206",
        "kecamatan": "820601",
        "desa": "8206012006",
        "tps": "8206012006003",
        "url": "82\/8206\/820601\/8206012006\/8206012006003.json",
        "nama": "TPS 003, SUBAIM, WASILE, HALMAHERA TIMUR, MALUKU UTARA"
    },
    {
        "provinsi": "82",
        "kabupaten": "8206",
        "kecamatan": "820601",
        "desa": "8206012006",
        "tps": "8206012006004",
        "url": "82\/8206\/820601\/8206012006\/8206012006004.json",
        "nama": "TPS 004, SUBAIM, WASILE, HALMAHERA TIMUR, MALUKU UTARA"
    },
    {
        "provinsi": "82",
        "kabupaten": "8206",
        "kecamatan": "820601",
        "desa": "8206012027",
        "tps": "8206012027001",
        "url": "82\/8206\/820601\/8206012027\/8206012027001.json",
        "nama": "TPS 001, WAISUBA, WASILE, HALMAHERA TIMUR, MALUKU UTARA"
    },
    {
        "provinsi": "82",
        "kabupaten": "8206",
        "kecamatan": "820601",
        "desa": "8206012027",
        "tps": "8206012027002",
        "url": "82\/8206\/820601\/8206012027\/8206012027002.json",
        "nama": "TPS 002, WAISUBA, WASILE, HALMAHERA TIMUR, MALUKU UTARA"
    },
    {
        "provinsi": "82",
        "kabupaten": "8206",
        "kecamatan": "820604",
        "desa": "8206042018",
        "tps": "8206042018001",
        "url": "82\/8206\/820604\/8206042018\/8206042018001.json",
        "nama": "TPS 001, AKE JAWI, WASILE SELATAN, HALMAHERA TIMUR, MALUKU UTARA"
    },
    {
        "provinsi": "82",
        "kabupaten": "8206",
        "kecamatan": "820604",
        "desa": "8206042018",
        "tps": "8206042018002",
        "url": "82\/8206\/820604\/8206042018\/8206042018002.json",
        "nama": "TPS 002, AKE JAWI, WASILE SELATAN, HALMAHERA TIMUR, MALUKU UTARA"
    },
    {
        "provinsi": "82",
        "kabupaten": "8206",
        "kecamatan": "820604",
        "desa": "8206042009",
        "tps": "8206042009001",
        "url": "82\/8206\/820604\/8206042009\/8206042009001.json",
        "nama": "TPS 001, BINAGARA, WASILE SELATAN, HALMAHERA TIMUR, MALUKU UTARA"
    },
    {
        "provinsi": "82",
        "kabupaten": "8206",
        "kecamatan": "820604",
        "desa": "8206042009",
        "tps": "8206042009002",
        "url": "82\/8206\/820604\/8206042009\/8206042009002.json",
        "nama": "TPS 002, BINAGARA, WASILE SELATAN, HALMAHERA TIMUR, MALUKU UTARA"
    },
    {
        "provinsi": "82",
        "kabupaten": "8206",
        "kecamatan": "820604",
        "desa": "8206042024",
        "tps": "8206042024001",
        "url": "82\/8206\/820604\/8206042024\/8206042024001.json",
        "nama": "TPS 001, BUKUTIO, WASILE SELATAN, HALMAHERA TIMUR, MALUKU UTARA"
    },
    {
        "provinsi": "82",
        "kabupaten": "8206",
        "kecamatan": "820604",
        "desa": "8206042019",
        "tps": "8206042019001",
        "url": "82\/8206\/820604\/8206042019\/8206042019001.json",
        "nama": "TPS 001, EKOR, WASILE SELATAN, HALMAHERA TIMUR, MALUKU UTARA"
    },
    {
        "provinsi": "82",
        "kabupaten": "8206",
        "kecamatan": "820604",
        "desa": "8206042019",
        "tps": "8206042019002",
        "url": "82\/8206\/820604\/8206042019\/8206042019002.json",
        "nama": "TPS 002, EKOR, WASILE SELATAN, HALMAHERA TIMUR, MALUKU UTARA"
    },
    {
        "provinsi": "82",
        "kabupaten": "8206",
        "kecamatan": "820604",
        "desa": "8206042020",
        "tps": "8206042020001",
        "url": "82\/8206\/820604\/8206042020\/8206042020001.json",
        "nama": "TPS 001, EKORINO, WASILE SELATAN, HALMAHERA TIMUR, MALUKU UTARA"
    },
    {
        "provinsi": "82",
        "kabupaten": "8206",
        "kecamatan": "820604",
        "desa": "8206042020",
        "tps": "8206042020002",
        "url": "82\/8206\/820604\/8206042020\/8206042020002.json",
        "nama": "TPS 002, EKORINO, WASILE SELATAN, HALMAHERA TIMUR, MALUKU UTARA"
    },
    {
        "provinsi": "82",
        "kabupaten": "8206",
        "kecamatan": "820604",
        "desa": "8206042008",
        "tps": "8206042008001",
        "url": "82\/8206\/820604\/8206042008\/8206042008001.json",
        "nama": "TPS 001, FAYAUL, WASILE SELATAN, HALMAHERA TIMUR, MALUKU UTARA"
    },
    {
        "provinsi": "82",
        "kabupaten": "8206",
        "kecamatan": "820604",
        "desa": "8206042008",
        "tps": "8206042008002",
        "url": "82\/8206\/820604\/8206042008\/8206042008002.json",
        "nama": "TPS 002, FAYAUL, WASILE SELATAN, HALMAHERA TIMUR, MALUKU UTARA"
    },
    {
        "provinsi": "82",
        "kabupaten": "8206",
        "kecamatan": "820604",
        "desa": "8206042017",
        "tps": "8206042017001",
        "url": "82\/8206\/820604\/8206042017\/8206042017001.json",
        "nama": "TPS 001, INO JAYA, WASILE SELATAN, HALMAHERA TIMUR, MALUKU UTARA"
    },
    {
        "provinsi": "82",
        "kabupaten": "8206",
        "kecamatan": "820604",
        "desa": "8206042017",
        "tps": "8206042017002",
        "url": "82\/8206\/820604\/8206042017\/8206042017002.json",
        "nama": "TPS 002, INO JAYA, WASILE SELATAN, HALMAHERA TIMUR, MALUKU UTARA"
    },
    {
        "provinsi": "82",
        "kabupaten": "8206",
        "kecamatan": "820604",
        "desa": "8206042021",
        "tps": "8206042021001",
        "url": "82\/8206\/820604\/8206042021\/8206042021001.json",
        "nama": "TPS 001, JIKO MOI, WASILE SELATAN, HALMAHERA TIMUR, MALUKU UTARA"
    },
    {
        "provinsi": "82",
        "kabupaten": "8206",
        "kecamatan": "820604",
        "desa": "8206042021",
        "tps": "8206042021002",
        "url": "82\/8206\/820604\/8206042021\/8206042021002.json",
        "nama": "TPS 002, JIKO MOI, WASILE SELATAN, HALMAHERA TIMUR, MALUKU UTARA"
    },
    {
        "provinsi": "82",
        "kabupaten": "8206",
        "kecamatan": "820604",
        "desa": "8206042003",
        "tps": "8206042003001",
        "url": "82\/8206\/820604\/8206042003\/8206042003001.json",
        "nama": "TPS 001, LOLEBA, WASILE SELATAN, HALMAHERA TIMUR, MALUKU UTARA"
    },
    {
        "provinsi": "82",
        "kabupaten": "8206",
        "kecamatan": "820604",
        "desa": "8206042003",
        "tps": "8206042003002",
        "url": "82\/8206\/820604\/8206042003\/8206042003002.json",
        "nama": "TPS 002, LOLEBA, WASILE SELATAN, HALMAHERA TIMUR, MALUKU UTARA"
    },
    {
        "provinsi": "82",
        "kabupaten": "8206",
        "kecamatan": "820604",
        "desa": "8206042003",
        "tps": "8206042003003",
        "url": "82\/8206\/820604\/8206042003\/8206042003003.json",
        "nama": "TPS 003, LOLEBA, WASILE SELATAN, HALMAHERA TIMUR, MALUKU UTARA"
    },
    {
        "provinsi": "82",
        "kabupaten": "8206",
        "kecamatan": "820604",
        "desa": "8206042006",
        "tps": "8206042006001",
        "url": "82\/8206\/820604\/8206042006\/8206042006001.json",
        "nama": "TPS 001, MINAMIN, WASILE SELATAN, HALMAHERA TIMUR, MALUKU UTARA"
    },
    {
        "provinsi": "82",
        "kabupaten": "8206",
        "kecamatan": "820604",
        "desa": "8206042006",
        "tps": "8206042006002",
        "url": "82\/8206\/820604\/8206042006\/8206042006002.json",
        "nama": "TPS 002, MINAMIN, WASILE SELATAN, HALMAHERA TIMUR, MALUKU UTARA"
    },
    {
        "provinsi": "82",
        "kabupaten": "8206",
        "kecamatan": "820604",
        "desa": "8206042014",
        "tps": "8206042014001",
        "url": "82\/8206\/820604\/8206042014\/8206042014001.json",
        "nama": "TPS 001, NANAS, WASILE SELATAN, HALMAHERA TIMUR, MALUKU UTARA"
    },
    {
        "provinsi": "82",
        "kabupaten": "8206",
        "kecamatan": "820604",
        "desa": "8206042014",
        "tps": "8206042014002",
        "url": "82\/8206\/820604\/8206042014\/8206042014002.json",
        "nama": "TPS 002, NANAS, WASILE SELATAN, HALMAHERA TIMUR, MALUKU UTARA"
    },
    {
        "provinsi": "82",
        "kabupaten": "8206",
        "kecamatan": "820604",
        "desa": "8206042002",
        "tps": "8206042002001",
        "url": "82\/8206\/820604\/8206042002\/8206042002001.json",
        "nama": "TPS 001, NUSA AMBO, WASILE SELATAN, HALMAHERA TIMUR, MALUKU UTARA"
    },
    {
        "provinsi": "82",
        "kabupaten": "8206",
        "kecamatan": "820604",
        "desa": "8206042002",
        "tps": "8206042002002",
        "url": "82\/8206\/820604\/8206042002\/8206042002002.json",
        "nama": "TPS 002, NUSA AMBO, WASILE SELATAN, HALMAHERA TIMUR, MALUKU UTARA"
    },
    {
        "provinsi": "82",
        "kabupaten": "8206",
        "kecamatan": "820604",
        "desa": "8206042001",
        "tps": "8206042001001",
        "url": "82\/8206\/820604\/8206042001\/8206042001001.json",
        "nama": "TPS 001, NUSA JAYA, WASILE SELATAN, HALMAHERA TIMUR, MALUKU UTARA"
    },
    {
        "provinsi": "82",
        "kabupaten": "8206",
        "kecamatan": "820604",
        "desa": "8206042001",
        "tps": "8206042001002",
        "url": "82\/8206\/820604\/8206042001\/8206042001002.json",
        "nama": "TPS 002, NUSA JAYA, WASILE SELATAN, HALMAHERA TIMUR, MALUKU UTARA"
    },
    {
        "provinsi": "82",
        "kabupaten": "8206",
        "kecamatan": "820604",
        "desa": "8206042005",
        "tps": "8206042005001",
        "url": "82\/8206\/820604\/8206042005\/8206042005001.json",
        "nama": "TPS 001, PINTATU, WASILE SELATAN, HALMAHERA TIMUR, MALUKU UTARA"
    },
    {
        "provinsi": "82",
        "kabupaten": "8206",
        "kecamatan": "820604",
        "desa": "8206042005",
        "tps": "8206042005002",
        "url": "82\/8206\/820604\/8206042005\/8206042005002.json",
        "nama": "TPS 002, PINTATU, WASILE SELATAN, HALMAHERA TIMUR, MALUKU UTARA"
    },
    {
        "provinsi": "82",
        "kabupaten": "8206",
        "kecamatan": "820604",
        "desa": "8206042013",
        "tps": "8206042013001",
        "url": "82\/8206\/820604\/8206042013\/8206042013001.json",
        "nama": "TPS 001, SAOLAT, WASILE SELATAN, HALMAHERA TIMUR, MALUKU UTARA"
    },
    {
        "provinsi": "82",
        "kabupaten": "8206",
        "kecamatan": "820604",
        "desa": "8206042013",
        "tps": "8206042013002",
        "url": "82\/8206\/820604\/8206042013\/8206042013002.json",
        "nama": "TPS 002, SAOLAT, WASILE SELATAN, HALMAHERA TIMUR, MALUKU UTARA"
    },
    {
        "provinsi": "82",
        "kabupaten": "8206",
        "kecamatan": "820604",
        "desa": "8206042007",
        "tps": "8206042007001",
        "url": "82\/8206\/820604\/8206042007\/8206042007001.json",
        "nama": "TPS 001, SARAMAAKE, WASILE SELATAN, HALMAHERA TIMUR, MALUKU UTARA"
    },
    {
        "provinsi": "82",
        "kabupaten": "8206",
        "kecamatan": "820604",
        "desa": "8206042007",
        "tps": "8206042007002",
        "url": "82\/8206\/820604\/8206042007\/8206042007002.json",
        "nama": "TPS 002, SARAMAAKE, WASILE SELATAN, HALMAHERA TIMUR, MALUKU UTARA"
    },
    {
        "provinsi": "82",
        "kabupaten": "8206",
        "kecamatan": "820604",
        "desa": "8206042016",
        "tps": "8206042016001",
        "url": "82\/8206\/820604\/8206042016\/8206042016001.json",
        "nama": "TPS 001, SONDO-SONDO, WASILE SELATAN, HALMAHERA TIMUR, MALUKU UTARA"
    },
    {
        "provinsi": "82",
        "kabupaten": "8206",
        "kecamatan": "820604",
        "desa": "8206042016",
        "tps": "8206042016002",
        "url": "82\/8206\/820604\/8206042016\/8206042016002.json",
        "nama": "TPS 002, SONDO-SONDO, WASILE SELATAN, HALMAHERA TIMUR, MALUKU UTARA"
    },
    {
        "provinsi": "82",
        "kabupaten": "8206",
        "kecamatan": "820604",
        "desa": "8206042012",
        "tps": "8206042012001",
        "url": "82\/8206\/820604\/8206042012\/8206042012001.json",
        "nama": "TPS 001, TABANALOU, WASILE SELATAN, HALMAHERA TIMUR, MALUKU UTARA"
    },
    {
        "provinsi": "82",
        "kabupaten": "8206",
        "kecamatan": "820604",
        "desa": "8206042012",
        "tps": "8206042012002",
        "url": "82\/8206\/820604\/8206042012\/8206042012002.json",
        "nama": "TPS 002, TABANALOU, WASILE SELATAN, HALMAHERA TIMUR, MALUKU UTARA"
    },
    {
        "provinsi": "82",
        "kabupaten": "8206",
        "kecamatan": "820604",
        "desa": "8206042015",
        "tps": "8206042015001",
        "url": "82\/8206\/820604\/8206042015\/8206042015001.json",
        "nama": "TPS 001, TALAGA JAYA, WASILE SELATAN, HALMAHERA TIMUR, MALUKU UTARA"
    },
    {
        "provinsi": "82",
        "kabupaten": "8206",
        "kecamatan": "820604",
        "desa": "8206042015",
        "tps": "8206042015002",
        "url": "82\/8206\/820604\/8206042015\/8206042015002.json",
        "nama": "TPS 002, TALAGA JAYA, WASILE SELATAN, HALMAHERA TIMUR, MALUKU UTARA"
    },
    {
        "provinsi": "82",
        "kabupaten": "8206",
        "kecamatan": "820604",
        "desa": "8206042022",
        "tps": "8206042022001",
        "url": "82\/8206\/820604\/8206042022\/8206042022001.json",
        "nama": "TPS 001, TANURE, WASILE SELATAN, HALMAHERA TIMUR, MALUKU UTARA"
    },
    {
        "provinsi": "82",
        "kabupaten": "8206",
        "kecamatan": "820604",
        "desa": "8206042011",
        "tps": "8206042011001",
        "url": "82\/8206\/820604\/8206042011\/8206042011001.json",
        "nama": "TPS 001, TOMARES, WASILE SELATAN, HALMAHERA TIMUR, MALUKU UTARA"
    },
    {
        "provinsi": "82",
        "kabupaten": "8206",
        "kecamatan": "820604",
        "desa": "8206042011",
        "tps": "8206042011002",
        "url": "82\/8206\/820604\/8206042011\/8206042011002.json",
        "nama": "TPS 002, TOMARES, WASILE SELATAN, HALMAHERA TIMUR, MALUKU UTARA"
    },
    {
        "provinsi": "82",
        "kabupaten": "8206",
        "kecamatan": "820604",
        "desa": "8206042004",
        "tps": "8206042004001",
        "url": "82\/8206\/820604\/8206042004\/8206042004001.json",
        "nama": "TPS 001, WAIJOI, WASILE SELATAN, HALMAHERA TIMUR, MALUKU UTARA"
    },
    {
        "provinsi": "82",
        "kabupaten": "8206",
        "kecamatan": "820604",
        "desa": "8206042004",
        "tps": "8206042004002",
        "url": "82\/8206\/820604\/8206042004\/8206042004002.json",
        "nama": "TPS 002, WAIJOI, WASILE SELATAN, HALMAHERA TIMUR, MALUKU UTARA"
    },
    {
        "provinsi": "82",
        "kabupaten": "8206",
        "kecamatan": "820604",
        "desa": "8206042010",
        "tps": "8206042010001",
        "url": "82\/8206\/820604\/8206042010\/8206042010001.json",
        "nama": "TPS 001, WASILE, WASILE SELATAN, HALMAHERA TIMUR, MALUKU UTARA"
    },
    {
        "provinsi": "82",
        "kabupaten": "8206",
        "kecamatan": "820604",
        "desa": "8206042010",
        "tps": "8206042010002",
        "url": "82\/8206\/820604\/8206042010\/8206042010002.json",
        "nama": "TPS 002, WASILE, WASILE SELATAN, HALMAHERA TIMUR, MALUKU UTARA"
    },
    {
        "provinsi": "82",
        "kabupaten": "8206",
        "kecamatan": "820604",
        "desa": "8206042023",
        "tps": "8206042023001",
        "url": "82\/8206\/820604\/8206042023\/8206042023001.json",
        "nama": "TPS 001, YAWAL, WASILE SELATAN, HALMAHERA TIMUR, MALUKU UTARA"
    },
    {
        "provinsi": "82",
        "kabupaten": "8206",
        "kecamatan": "820605",
        "desa": "8206052006",
        "tps": "8206052006001",
        "url": "82\/8206\/820605\/8206052006\/8206052006001.json",
        "nama": "TPS 001, BOKIMAAKE, WASILE TENGAH, HALMAHERA TIMUR, MALUKU UTARA"
    },
    {
        "provinsi": "82",
        "kabupaten": "8206",
        "kecamatan": "820605",
        "desa": "8206052006",
        "tps": "8206052006002",
        "url": "82\/8206\/820605\/8206052006\/8206052006002.json",
        "nama": "TPS 002, BOKIMAAKE, WASILE TENGAH, HALMAHERA TIMUR, MALUKU UTARA"
    },
    {
        "provinsi": "82",
        "kabupaten": "8206",
        "kecamatan": "820605",
        "desa": "8206052004",
        "tps": "8206052004001",
        "url": "82\/8206\/820605\/8206052004\/8206052004001.json",
        "nama": "TPS 001, FOLI, WASILE TENGAH, HALMAHERA TIMUR, MALUKU UTARA"
    },
    {
        "provinsi": "82",
        "kabupaten": "8206",
        "kecamatan": "820605",
        "desa": "8206052004",
        "tps": "8206052004002",
        "url": "82\/8206\/820605\/8206052004\/8206052004002.json",
        "nama": "TPS 002, FOLI, WASILE TENGAH, HALMAHERA TIMUR, MALUKU UTARA"
    },
    {
        "provinsi": "82",
        "kabupaten": "8206",
        "kecamatan": "820605",
        "desa": "8206052004",
        "tps": "8206052004003",
        "url": "82\/8206\/820605\/8206052004\/8206052004003.json",
        "nama": "TPS 003, FOLI, WASILE TENGAH, HALMAHERA TIMUR, MALUKU UTARA"
    },
    {
        "provinsi": "82",
        "kabupaten": "8206",
        "kecamatan": "820605",
        "desa": "8206052001",
        "tps": "8206052001001",
        "url": "82\/8206\/820605\/8206052001\/8206052001001.json",
        "nama": "TPS 001, HATE TABAKO, WASILE TENGAH, HALMAHERA TIMUR, MALUKU UTARA"
    },
    {
        "provinsi": "82",
        "kabupaten": "8206",
        "kecamatan": "820605",
        "desa": "8206052001",
        "tps": "8206052001002",
        "url": "82\/8206\/820605\/8206052001\/8206052001002.json",
        "nama": "TPS 002, HATE TABAKO, WASILE TENGAH, HALMAHERA TIMUR, MALUKU UTARA"
    },
    {
        "provinsi": "82",
        "kabupaten": "8206",
        "kecamatan": "820605",
        "desa": "8206052001",
        "tps": "8206052001003",
        "url": "82\/8206\/820605\/8206052001\/8206052001003.json",
        "nama": "TPS 003, HATE TABAKO, WASILE TENGAH, HALMAHERA TIMUR, MALUKU UTARA"
    },
    {
        "provinsi": "82",
        "kabupaten": "8206",
        "kecamatan": "820605",
        "desa": "8206052008",
        "tps": "8206052008001",
        "url": "82\/8206\/820605\/8206052008\/8206052008001.json",
        "nama": "TPS 001, KAKARAINO, WASILE TENGAH, HALMAHERA TIMUR, MALUKU UTARA"
    },
    {
        "provinsi": "82",
        "kabupaten": "8206",
        "kecamatan": "820605",
        "desa": "8206052008",
        "tps": "8206052008002",
        "url": "82\/8206\/820605\/8206052008\/8206052008002.json",
        "nama": "TPS 002, KAKARAINO, WASILE TENGAH, HALMAHERA TIMUR, MALUKU UTARA"
    },
    {
        "provinsi": "82",
        "kabupaten": "8206",
        "kecamatan": "820605",
        "desa": "8206052002",
        "tps": "8206052002001",
        "url": "82\/8206\/820605\/8206052002\/8206052002001.json",
        "nama": "TPS 001, LOLOBATA, WASILE TENGAH, HALMAHERA TIMUR, MALUKU UTARA"
    },
    {
        "provinsi": "82",
        "kabupaten": "8206",
        "kecamatan": "820605",
        "desa": "8206052002",
        "tps": "8206052002002",
        "url": "82\/8206\/820605\/8206052002\/8206052002002.json",
        "nama": "TPS 002, LOLOBATA, WASILE TENGAH, HALMAHERA TIMUR, MALUKU UTARA"
    },
    {
        "provinsi": "82",
        "kabupaten": "8206",
        "kecamatan": "820605",
        "desa": "8206052002",
        "tps": "8206052002003",
        "url": "82\/8206\/820605\/8206052002\/8206052002003.json",
        "nama": "TPS 003, LOLOBATA, WASILE TENGAH, HALMAHERA TIMUR, MALUKU UTARA"
    },
    {
        "provinsi": "82",
        "kabupaten": "8206",
        "kecamatan": "820605",
        "desa": "8206052005",
        "tps": "8206052005001",
        "url": "82\/8206\/820605\/8206052005\/8206052005001.json",
        "nama": "TPS 001, NYAOLAKO, WASILE TENGAH, HALMAHERA TIMUR, MALUKU UTARA"
    },
    {
        "provinsi": "82",
        "kabupaten": "8206",
        "kecamatan": "820605",
        "desa": "8206052003",
        "tps": "8206052003001",
        "url": "82\/8206\/820605\/8206052003\/8206052003001.json",
        "nama": "TPS 001, PUAO, WASILE TENGAH, HALMAHERA TIMUR, MALUKU UTARA"
    },
    {
        "provinsi": "82",
        "kabupaten": "8206",
        "kecamatan": "820605",
        "desa": "8206052003",
        "tps": "8206052003002",
        "url": "82\/8206\/820605\/8206052003\/8206052003002.json",
        "nama": "TPS 002, PUAO, WASILE TENGAH, HALMAHERA TIMUR, MALUKU UTARA"
    },
    {
        "provinsi": "82",
        "kabupaten": "8206",
        "kecamatan": "820605",
        "desa": "8206052007",
        "tps": "8206052007001",
        "url": "82\/8206\/820605\/8206052007\/8206052007001.json",
        "nama": "TPS 001, SILALAYANG, WASILE TENGAH, HALMAHERA TIMUR, MALUKU UTARA"
    },
    {
        "provinsi": "82",
        "kabupaten": "8206",
        "kecamatan": "820605",
        "desa": "8206052007",
        "tps": "8206052007002",
        "url": "82\/8206\/820605\/8206052007\/8206052007002.json",
        "nama": "TPS 002, SILALAYANG, WASILE TENGAH, HALMAHERA TIMUR, MALUKU UTARA"
    },
    {
        "provinsi": "82",
        "kabupaten": "8206",
        "kecamatan": "820607",
        "desa": "8206072003",
        "tps": "8206072003001",
        "url": "82\/8206\/820607\/8206072003\/8206072003001.json",
        "nama": "TPS 001, AKEDAGA, WASILE TIMUR, HALMAHERA TIMUR, MALUKU UTARA"
    },
    {
        "provinsi": "82",
        "kabupaten": "8206",
        "kecamatan": "820607",
        "desa": "8206072003",
        "tps": "8206072003002",
        "url": "82\/8206\/820607\/8206072003\/8206072003002.json",
        "nama": "TPS 002, AKEDAGA, WASILE TIMUR, HALMAHERA TIMUR, MALUKU UTARA"
    },
    {
        "provinsi": "82",
        "kabupaten": "8206",
        "kecamatan": "820607",
        "desa": "8206072003",
        "tps": "8206072003003",
        "url": "82\/8206\/820607\/8206072003\/8206072003003.json",
        "nama": "TPS 003, AKEDAGA, WASILE TIMUR, HALMAHERA TIMUR, MALUKU UTARA"
    },
    {
        "provinsi": "82",
        "kabupaten": "8206",
        "kecamatan": "820607",
        "desa": "8206072003",
        "tps": "8206072003004",
        "url": "82\/8206\/820607\/8206072003\/8206072003004.json",
        "nama": "TPS 004, AKEDAGA, WASILE TIMUR, HALMAHERA TIMUR, MALUKU UTARA"
    },
    {
        "provinsi": "82",
        "kabupaten": "8206",
        "kecamatan": "820607",
        "desa": "8206072002",
        "tps": "8206072002001",
        "url": "82\/8206\/820607\/8206072002\/8206072002001.json",
        "nama": "TPS 001, DAKAINO, WASILE TIMUR, HALMAHERA TIMUR, MALUKU UTARA"
    },
    {
        "provinsi": "82",
        "kabupaten": "8206",
        "kecamatan": "820607",
        "desa": "8206072002",
        "tps": "8206072002002",
        "url": "82\/8206\/820607\/8206072002\/8206072002002.json",
        "nama": "TPS 002, DAKAINO, WASILE TIMUR, HALMAHERA TIMUR, MALUKU UTARA"
    },
    {
        "provinsi": "82",
        "kabupaten": "8206",
        "kecamatan": "820607",
        "desa": "8206072002",
        "tps": "8206072002003",
        "url": "82\/8206\/820607\/8206072002\/8206072002003.json",
        "nama": "TPS 003, DAKAINO, WASILE TIMUR, HALMAHERA TIMUR, MALUKU UTARA"
    },
    {
        "provinsi": "82",
        "kabupaten": "8206",
        "kecamatan": "820607",
        "desa": "8206072002",
        "tps": "8206072002004",
        "url": "82\/8206\/820607\/8206072002\/8206072002004.json",
        "nama": "TPS 004, DAKAINO, WASILE TIMUR, HALMAHERA TIMUR, MALUKU UTARA"
    },
    {
        "provinsi": "82",
        "kabupaten": "8206",
        "kecamatan": "820607",
        "desa": "8206072001",
        "tps": "8206072001001",
        "url": "82\/8206\/820607\/8206072001\/8206072001001.json",
        "nama": "TPS 001, DODAGA, WASILE TIMUR, HALMAHERA TIMUR, MALUKU UTARA"
    },
    {
        "provinsi": "82",
        "kabupaten": "8206",
        "kecamatan": "820607",
        "desa": "8206072001",
        "tps": "8206072001002",
        "url": "82\/8206\/820607\/8206072001\/8206072001002.json",
        "nama": "TPS 002, DODAGA, WASILE TIMUR, HALMAHERA TIMUR, MALUKU UTARA"
    },
    {
        "provinsi": "82",
        "kabupaten": "8206",
        "kecamatan": "820607",
        "desa": "8206072001",
        "tps": "8206072001003",
        "url": "82\/8206\/820607\/8206072001\/8206072001003.json",
        "nama": "TPS 003, DODAGA, WASILE TIMUR, HALMAHERA TIMUR, MALUKU UTARA"
    },
    {
        "provinsi": "82",
        "kabupaten": "8206",
        "kecamatan": "820607",
        "desa": "8206072001",
        "tps": "8206072001004",
        "url": "82\/8206\/820607\/8206072001\/8206072001004.json",
        "nama": "TPS 004, DODAGA, WASILE TIMUR, HALMAHERA TIMUR, MALUKU UTARA"
    },
    {
        "provinsi": "82",
        "kabupaten": "8206",
        "kecamatan": "820607",
        "desa": "8206072001",
        "tps": "8206072001005",
        "url": "82\/8206\/820607\/8206072001\/8206072001005.json",
        "nama": "TPS 005, DODAGA, WASILE TIMUR, HALMAHERA TIMUR, MALUKU UTARA"
    },
    {
        "provinsi": "82",
        "kabupaten": "8206",
        "kecamatan": "820607",
        "desa": "8206072001",
        "tps": "8206072001006",
        "url": "82\/8206\/820607\/8206072001\/8206072001006.json",
        "nama": "TPS 006, DODAGA, WASILE TIMUR, HALMAHERA TIMUR, MALUKU UTARA"
    },
    {
        "provinsi": "82",
        "kabupaten": "8206",
        "kecamatan": "820607",
        "desa": "8206072001",
        "tps": "8206072001007",
        "url": "82\/8206\/820607\/8206072001\/8206072001007.json",
        "nama": "TPS 007, DODAGA, WASILE TIMUR, HALMAHERA TIMUR, MALUKU UTARA"
    },
    {
        "provinsi": "82",
        "kabupaten": "8206",
        "kecamatan": "820607",
        "desa": "8206072001",
        "tps": "8206072001008",
        "url": "82\/8206\/820607\/8206072001\/8206072001008.json",
        "nama": "TPS 008, DODAGA, WASILE TIMUR, HALMAHERA TIMUR, MALUKU UTARA"
    },
    {
        "provinsi": "82",
        "kabupaten": "8206",
        "kecamatan": "820607",
        "desa": "8206072001",
        "tps": "8206072001009",
        "url": "82\/8206\/820607\/8206072001\/8206072001009.json",
        "nama": "TPS 009, DODAGA, WASILE TIMUR, HALMAHERA TIMUR, MALUKU UTARA"
    },
    {
        "provinsi": "82",
        "kabupaten": "8206",
        "kecamatan": "820607",
        "desa": "8206072007",
        "tps": "8206072007001",
        "url": "82\/8206\/820607\/8206072007\/8206072007001.json",
        "nama": "TPS 001, RAWAMANGUN, WASILE TIMUR, HALMAHERA TIMUR, MALUKU UTARA"
    },
    {
        "provinsi": "82",
        "kabupaten": "8206",
        "kecamatan": "820607",
        "desa": "8206072007",
        "tps": "8206072007002",
        "url": "82\/8206\/820607\/8206072007\/8206072007002.json",
        "nama": "TPS 002, RAWAMANGUN, WASILE TIMUR, HALMAHERA TIMUR, MALUKU UTARA"
    },
    {
        "provinsi": "82",
        "kabupaten": "8206",
        "kecamatan": "820607",
        "desa": "8206072007",
        "tps": "8206072007003",
        "url": "82\/8206\/820607\/8206072007\/8206072007003.json",
        "nama": "TPS 003, RAWAMANGUN, WASILE TIMUR, HALMAHERA TIMUR, MALUKU UTARA"
    },
    {
        "provinsi": "82",
        "kabupaten": "8206",
        "kecamatan": "820607",
        "desa": "8206072008",
        "tps": "8206072008001",
        "url": "82\/8206\/820607\/8206072008\/8206072008001.json",
        "nama": "TPS 001, SIDOMULYO, WASILE TIMUR, HALMAHERA TIMUR, MALUKU UTARA"
    },
    {
        "provinsi": "82",
        "kabupaten": "8206",
        "kecamatan": "820607",
        "desa": "8206072008",
        "tps": "8206072008002",
        "url": "82\/8206\/820607\/8206072008\/8206072008002.json",
        "nama": "TPS 002, SIDOMULYO, WASILE TIMUR, HALMAHERA TIMUR, MALUKU UTARA"
    },
    {
        "provinsi": "82",
        "kabupaten": "8206",
        "kecamatan": "820607",
        "desa": "8206072008",
        "tps": "8206072008003",
        "url": "82\/8206\/820607\/8206072008\/8206072008003.json",
        "nama": "TPS 003, SIDOMULYO, WASILE TIMUR, HALMAHERA TIMUR, MALUKU UTARA"
    },
    {
        "provinsi": "82",
        "kabupaten": "8206",
        "kecamatan": "820607",
        "desa": "8206072008",
        "tps": "8206072008004",
        "url": "82\/8206\/820607\/8206072008\/8206072008004.json",
        "nama": "TPS 004, SIDOMULYO, WASILE TIMUR, HALMAHERA TIMUR, MALUKU UTARA"
    },
    {
        "provinsi": "82",
        "kabupaten": "8206",
        "kecamatan": "820607",
        "desa": "8206072008",
        "tps": "8206072008005",
        "url": "82\/8206\/820607\/8206072008\/8206072008005.json",
        "nama": "TPS 005, SIDOMULYO, WASILE TIMUR, HALMAHERA TIMUR, MALUKU UTARA"
    },
    {
        "provinsi": "82",
        "kabupaten": "8206",
        "kecamatan": "820607",
        "desa": "8206072004",
        "tps": "8206072004001",
        "url": "82\/8206\/820607\/8206072004\/8206072004001.json",
        "nama": "TPS 001, TOBOINO, WASILE TIMUR, HALMAHERA TIMUR, MALUKU UTARA"
    },
    {
        "provinsi": "82",
        "kabupaten": "8206",
        "kecamatan": "820607",
        "desa": "8206072004",
        "tps": "8206072004002",
        "url": "82\/8206\/820607\/8206072004\/8206072004002.json",
        "nama": "TPS 002, TOBOINO, WASILE TIMUR, HALMAHERA TIMUR, MALUKU UTARA"
    },
    {
        "provinsi": "82",
        "kabupaten": "8206",
        "kecamatan": "820607",
        "desa": "8206072004",
        "tps": "8206072004003",
        "url": "82\/8206\/820607\/8206072004\/8206072004003.json",
        "nama": "TPS 003, TOBOINO, WASILE TIMUR, HALMAHERA TIMUR, MALUKU UTARA"
    },
    {
        "provinsi": "82",
        "kabupaten": "8206",
        "kecamatan": "820607",
        "desa": "8206072004",
        "tps": "8206072004004",
        "url": "82\/8206\/820607\/8206072004\/8206072004004.json",
        "nama": "TPS 004, TOBOINO, WASILE TIMUR, HALMAHERA TIMUR, MALUKU UTARA"
    },
    {
        "provinsi": "82",
        "kabupaten": "8206",
        "kecamatan": "820607",
        "desa": "8206072005",
        "tps": "8206072005001",
        "url": "82\/8206\/820607\/8206072005\/8206072005001.json",
        "nama": "TPS 001, TUTULING JAYA, WASILE TIMUR, HALMAHERA TIMUR, MALUKU UTARA"
    },
    {
        "provinsi": "82",
        "kabupaten": "8206",
        "kecamatan": "820607",
        "desa": "8206072005",
        "tps": "8206072005002",
        "url": "82\/8206\/820607\/8206072005\/8206072005002.json",
        "nama": "TPS 002, TUTULING JAYA, WASILE TIMUR, HALMAHERA TIMUR, MALUKU UTARA"
    },
    {
        "provinsi": "82",
        "kabupaten": "8206",
        "kecamatan": "820607",
        "desa": "8206072005",
        "tps": "8206072005003",
        "url": "82\/8206\/820607\/8206072005\/8206072005003.json",
        "nama": "TPS 003, TUTULING JAYA, WASILE TIMUR, HALMAHERA TIMUR, MALUKU UTARA"
    },
    {
        "provinsi": "82",
        "kabupaten": "8206",
        "kecamatan": "820607",
        "desa": "8206072005",
        "tps": "8206072005004",
        "url": "82\/8206\/820607\/8206072005\/8206072005004.json",
        "nama": "TPS 004, TUTULING JAYA, WASILE TIMUR, HALMAHERA TIMUR, MALUKU UTARA"
    },
    {
        "provinsi": "82",
        "kabupaten": "8206",
        "kecamatan": "820607",
        "desa": "8206072005",
        "tps": "8206072005005",
        "url": "82\/8206\/820607\/8206072005\/8206072005005.json",
        "nama": "TPS 005, TUTULING JAYA, WASILE TIMUR, HALMAHERA TIMUR, MALUKU UTARA"
    },
    {
        "provinsi": "82",
        "kabupaten": "8206",
        "kecamatan": "820607",
        "desa": "8206072006",
        "tps": "8206072006001",
        "url": "82\/8206\/820607\/8206072006\/8206072006001.json",
        "nama": "TPS 001, WOKA JAYA, WASILE TIMUR, HALMAHERA TIMUR, MALUKU UTARA"
    },
    {
        "provinsi": "82",
        "kabupaten": "8206",
        "kecamatan": "820607",
        "desa": "8206072006",
        "tps": "8206072006002",
        "url": "82\/8206\/820607\/8206072006\/8206072006002.json",
        "nama": "TPS 002, WOKA JAYA, WASILE TIMUR, HALMAHERA TIMUR, MALUKU UTARA"
    },
    {
        "provinsi": "82",
        "kabupaten": "8206",
        "kecamatan": "820607",
        "desa": "8206072006",
        "tps": "8206072006003",
        "url": "82\/8206\/820607\/8206072006\/8206072006003.json",
        "nama": "TPS 003, WOKA JAYA, WASILE TIMUR, HALMAHERA TIMUR, MALUKU UTARA"
    },
    {
        "provinsi": "82",
        "kabupaten": "8206",
        "kecamatan": "820606",
        "desa": "8206062005",
        "tps": "8206062005001",
        "url": "82\/8206\/820606\/8206062005\/8206062005001.json",
        "nama": "TPS 001, BOLOLO, WASILE UTARA, HALMAHERA TIMUR, MALUKU UTARA"
    },
    {
        "provinsi": "82",
        "kabupaten": "8206",
        "kecamatan": "820606",
        "desa": "8206062005",
        "tps": "8206062005002",
        "url": "82\/8206\/820606\/8206062005\/8206062005002.json",
        "nama": "TPS 002, BOLOLO, WASILE UTARA, HALMAHERA TIMUR, MALUKU UTARA"
    },
    {
        "provinsi": "82",
        "kabupaten": "8206",
        "kecamatan": "820606",
        "desa": "8206062005",
        "tps": "8206062005003",
        "url": "82\/8206\/820606\/8206062005\/8206062005003.json",
        "nama": "TPS 003, BOLOLO, WASILE UTARA, HALMAHERA TIMUR, MALUKU UTARA"
    },
    {
        "provinsi": "82",
        "kabupaten": "8206",
        "kecamatan": "820606",
        "desa": "8206062007",
        "tps": "8206062007001",
        "url": "82\/8206\/820606\/8206062007\/8206062007001.json",
        "nama": "TPS 001, DOWONGI JAYA, WASILE UTARA, HALMAHERA TIMUR, MALUKU UTARA"
    },
    {
        "provinsi": "82",
        "kabupaten": "8206",
        "kecamatan": "820606",
        "desa": "8206062006",
        "tps": "8206062006001",
        "url": "82\/8206\/820606\/8206062006\/8206062006001.json",
        "nama": "TPS 001, HILAITETOR, WASILE UTARA, HALMAHERA TIMUR, MALUKU UTARA"
    },
    {
        "provinsi": "82",
        "kabupaten": "8206",
        "kecamatan": "820606",
        "desa": "8206062006",
        "tps": "8206062006002",
        "url": "82\/8206\/820606\/8206062006\/8206062006002.json",
        "nama": "TPS 002, HILAITETOR, WASILE UTARA, HALMAHERA TIMUR, MALUKU UTARA"
    },
    {
        "provinsi": "82",
        "kabupaten": "8206",
        "kecamatan": "820606",
        "desa": "8206062006",
        "tps": "8206062006003",
        "url": "82\/8206\/820606\/8206062006\/8206062006003.json",
        "nama": "TPS 003, HILAITETOR, WASILE UTARA, HALMAHERA TIMUR, MALUKU UTARA"
    },
    {
        "provinsi": "82",
        "kabupaten": "8206",
        "kecamatan": "820606",
        "desa": "8206062002",
        "tps": "8206062002001",
        "url": "82\/8206\/820606\/8206062002\/8206062002001.json",
        "nama": "TPS 001, IGA, WASILE UTARA, HALMAHERA TIMUR, MALUKU UTARA"
    },
    {
        "provinsi": "82",
        "kabupaten": "8206",
        "kecamatan": "820606",
        "desa": "8206062002",
        "tps": "8206062002002",
        "url": "82\/8206\/820606\/8206062002\/8206062002002.json",
        "nama": "TPS 002, IGA, WASILE UTARA, HALMAHERA TIMUR, MALUKU UTARA"
    },
    {
        "provinsi": "82",
        "kabupaten": "8206",
        "kecamatan": "820606",
        "desa": "8206062002",
        "tps": "8206062002003",
        "url": "82\/8206\/820606\/8206062002\/8206062002003.json",
        "nama": "TPS 003, IGA, WASILE UTARA, HALMAHERA TIMUR, MALUKU UTARA"
    },
    {
        "provinsi": "82",
        "kabupaten": "8206",
        "kecamatan": "820606",
        "desa": "8206062001",
        "tps": "8206062001001",
        "url": "82\/8206\/820606\/8206062001\/8206062001001.json",
        "nama": "TPS 001, LABI-LABI, WASILE UTARA, HALMAHERA TIMUR, MALUKU UTARA"
    },
    {
        "provinsi": "82",
        "kabupaten": "8206",
        "kecamatan": "820606",
        "desa": "8206062001",
        "tps": "8206062001002",
        "url": "82\/8206\/820606\/8206062001\/8206062001002.json",
        "nama": "TPS 002, LABI-LABI, WASILE UTARA, HALMAHERA TIMUR, MALUKU UTARA"
    },
    {
        "provinsi": "82",
        "kabupaten": "8206",
        "kecamatan": "820606",
        "desa": "8206062008",
        "tps": "8206062008001",
        "url": "82\/8206\/820606\/8206062008\/8206062008001.json",
        "nama": "TPS 001, MAJIKO TONGONE, WASILE UTARA, HALMAHERA TIMUR, MALUKU UTARA"
    },
    {
        "provinsi": "82",
        "kabupaten": "8206",
        "kecamatan": "820606",
        "desa": "8206062008",
        "tps": "8206062008002",
        "url": "82\/8206\/820606\/8206062008\/8206062008002.json",
        "nama": "TPS 002, MAJIKO TONGONE, WASILE UTARA, HALMAHERA TIMUR, MALUKU UTARA"
    },
    {
        "provinsi": "82",
        "kabupaten": "8206",
        "kecamatan": "820606",
        "desa": "8206062004",
        "tps": "8206062004001",
        "url": "82\/8206\/820606\/8206062004\/8206062004001.json",
        "nama": "TPS 001, MARIMOI, WASILE UTARA, HALMAHERA TIMUR, MALUKU UTARA"
    },
    {
        "provinsi": "82",
        "kabupaten": "8206",
        "kecamatan": "820606",
        "desa": "8206062003",
        "tps": "8206062003001",
        "url": "82\/8206\/820606\/8206062003\/8206062003001.json",
        "nama": "TPS 001, TATAM, WASILE UTARA, HALMAHERA TIMUR, MALUKU UTARA"
    },
    {
        "provinsi": "82",
        "kabupaten": "8206",
        "kecamatan": "820606",
        "desa": "8206062003",
        "tps": "8206062003002",
        "url": "82\/8206\/820606\/8206062003\/8206062003002.json",
        "nama": "TPS 002, TATAM, WASILE UTARA, HALMAHERA TIMUR, MALUKU UTARA"
    }
]