[
    {
        "provinsi": "33",
        "kabupaten": "3312",
        "kecamatan": "331218",
        "desa": "3312182001",
        "tps": "3312182001006",
        "nama": "TPS 006, DOMAS, BULUKERTO, WONOGIRI, JAWA TENGAH",
        "selisih": 300,
        "url": "https:\/\/pemilu2024.kpu.go.id\/pilpres\/hitung-suara\/33\/3312\/331218\/3312182001\/3312182001006"
    },
    {
        "provinsi": "33",
        "kabupaten": "3312",
        "kecamatan": "331218",
        "desa": "3312182008",
        "tps": "3312182008002",
        "nama": "TPS 002, SUGIHAN, BULUKERTO, WONOGIRI, JAWA TENGAH",
        "selisih": 800,
        "url": "https:\/\/pemilu2024.kpu.go.id\/pilpres\/hitung-suara\/33\/3312\/331218\/3312182008\/3312182008002"
    },
    {
        "provinsi": "33",
        "kabupaten": "3312",
        "kecamatan": "331208",
        "desa": "3312082006",
        "tps": "3312082006004",
        "nama": "TPS 004, BALEHARJO, EROMOKO, WONOGIRI, JAWA TENGAH",
        "selisih": -5,
        "url": "https:\/\/pemilu2024.kpu.go.id\/pilpres\/hitung-suara\/33\/3312\/331208\/3312082006\/3312082006004"
    },
    {
        "provinsi": "33",
        "kabupaten": "3312",
        "kecamatan": "331208",
        "desa": "3312082006",
        "tps": "3312082006009",
        "nama": "TPS 009, BALEHARJO, EROMOKO, WONOGIRI, JAWA TENGAH",
        "selisih": 4,
        "url": "https:\/\/pemilu2024.kpu.go.id\/pilpres\/hitung-suara\/33\/3312\/331208\/3312082006\/3312082006009"
    },
    {
        "provinsi": "33",
        "kabupaten": "3312",
        "kecamatan": "331208",
        "desa": "3312082008",
        "tps": "3312082008010",
        "nama": "TPS 010, MINGGARHARJO, EROMOKO, WONOGIRI, JAWA TENGAH",
        "selisih": -112,
        "url": "https:\/\/pemilu2024.kpu.go.id\/pilpres\/hitung-suara\/33\/3312\/331208\/3312082008\/3312082008010"
    },
    {
        "provinsi": "33",
        "kabupaten": "3312",
        "kecamatan": "331222",
        "desa": "3312222010",
        "tps": "3312222010011",
        "nama": "TPS 011, GIRIWARNO, GIRIMARTO, WONOGIRI, JAWA TENGAH",
        "selisih": -5,
        "url": "https:\/\/pemilu2024.kpu.go.id\/pilpres\/hitung-suara\/33\/3312\/331222\/3312222010\/3312222010011"
    },
    {
        "provinsi": "33",
        "kabupaten": "3312",
        "kecamatan": "331222",
        "desa": "3312222008",
        "tps": "3312222008010",
        "nama": "TPS 010, TAMBAKMERANG, GIRIMARTO, WONOGIRI, JAWA TENGAH",
        "selisih": 27,
        "url": "https:\/\/pemilu2024.kpu.go.id\/pilpres\/hitung-suara\/33\/3312\/331222\/3312222008\/3312222008010"
    },
    {
        "provinsi": "33",
        "kabupaten": "3312",
        "kecamatan": "331202",
        "desa": "3312021004",
        "tps": "3312021004006",
        "nama": "TPS 006, BAYEMHARJO, GIRITONTRO, WONOGIRI, JAWA TENGAH",
        "selisih": -1,
        "url": "https:\/\/pemilu2024.kpu.go.id\/pilpres\/hitung-suara\/33\/3312\/331202\/3312021004\/3312021004006"
    },
    {
        "provinsi": "33",
        "kabupaten": "3312",
        "kecamatan": "331203",
        "desa": "3312031011",
        "tps": "3312031011003",
        "nama": "TPS 003, GIRIWOYO, GIRIWOYO, WONOGIRI, JAWA TENGAH",
        "selisih": 100,
        "url": "https:\/\/pemilu2024.kpu.go.id\/pilpres\/hitung-suara\/33\/3312\/331203\/3312031011\/3312031011003"
    },
    {
        "provinsi": "33",
        "kabupaten": "3312",
        "kecamatan": "331221",
        "desa": "3312211005",
        "tps": "3312211005009",
        "nama": "TPS 009, JATIPURNO, JATIPURNO, WONOGIRI, JAWA TENGAH",
        "selisih": -100,
        "url": "https:\/\/pemilu2024.kpu.go.id\/pilpres\/hitung-suara\/33\/3312\/331221\/3312211005\/3312211005009"
    },
    {
        "provinsi": "33",
        "kabupaten": "3312",
        "kecamatan": "331215",
        "desa": "3312152004",
        "tps": "3312152004008",
        "nama": "TPS 008, DAWUNGAN, JATIROTO, WONOGIRI, JAWA TENGAH",
        "selisih": -1,
        "url": "https:\/\/pemilu2024.kpu.go.id\/pilpres\/hitung-suara\/33\/3312\/331215\/3312152004\/3312152004008"
    },
    {
        "provinsi": "33",
        "kabupaten": "3312",
        "kecamatan": "331215",
        "desa": "3312152013",
        "tps": "3312152013003",
        "nama": "TPS 003, DUREN, JATIROTO, WONOGIRI, JAWA TENGAH",
        "selisih": 4,
        "url": "https:\/\/pemilu2024.kpu.go.id\/pilpres\/hitung-suara\/33\/3312\/331215\/3312152013\/3312152013003"
    },
    {
        "provinsi": "33",
        "kabupaten": "3312",
        "kecamatan": "331215",
        "desa": "3312152012",
        "tps": "3312152012003",
        "nama": "TPS 003, SUGIHAN, JATIROTO, WONOGIRI, JAWA TENGAH",
        "selisih": -3,
        "url": "https:\/\/pemilu2024.kpu.go.id\/pilpres\/hitung-suara\/33\/3312\/331215\/3312152012\/3312152012003"
    },
    {
        "provinsi": "33",
        "kabupaten": "3312",
        "kecamatan": "331216",
        "desa": "3312162006",
        "tps": "3312162006003",
        "nama": "TPS 003, MIRI, KISMANTORO, WONOGIRI, JAWA TENGAH",
        "selisih": 4,
        "url": "https:\/\/pemilu2024.kpu.go.id\/pilpres\/hitung-suara\/33\/3312\/331216\/3312162006\/3312162006003"
    },
    {
        "provinsi": "33",
        "kabupaten": "3312",
        "kecamatan": "331216",
        "desa": "3312162006",
        "tps": "3312162006010",
        "nama": "TPS 010, MIRI, KISMANTORO, WONOGIRI, JAWA TENGAH",
        "selisih": 669,
        "url": "https:\/\/pemilu2024.kpu.go.id\/pilpres\/hitung-suara\/33\/3312\/331216\/3312162006\/3312162006010"
    },
    {
        "provinsi": "33",
        "kabupaten": "3312",
        "kecamatan": "331210",
        "desa": "3312101006",
        "tps": "3312101006002",
        "nama": "TPS 002, PAGUTAN, MANYARAN, WONOGIRI, JAWA TENGAH",
        "selisih": 45,
        "url": "https:\/\/pemilu2024.kpu.go.id\/pilpres\/hitung-suara\/33\/3312\/331210\/3312101006\/3312101006002"
    },
    {
        "provinsi": "33",
        "kabupaten": "3312",
        "kecamatan": "331210",
        "desa": "3312101006",
        "tps": "3312101006007",
        "nama": "TPS 007, PAGUTAN, MANYARAN, WONOGIRI, JAWA TENGAH",
        "selisih": 149,
        "url": "https:\/\/pemilu2024.kpu.go.id\/pilpres\/hitung-suara\/33\/3312\/331210\/3312101006\/3312101006007"
    },
    {
        "provinsi": "33",
        "kabupaten": "3312",
        "kecamatan": "331213",
        "desa": "3312132001",
        "tps": "3312132001007",
        "nama": "TPS 007, GEMAWANG, NGADIROJO, WONOGIRI, JAWA TENGAH",
        "selisih": -5,
        "url": "https:\/\/pemilu2024.kpu.go.id\/pilpres\/hitung-suara\/33\/3312\/331213\/3312132001\/3312132001007"
    },
    {
        "provinsi": "33",
        "kabupaten": "3312",
        "kecamatan": "331213",
        "desa": "3312132001",
        "tps": "3312132001012",
        "nama": "TPS 012, GEMAWANG, NGADIROJO, WONOGIRI, JAWA TENGAH",
        "selisih": 2,
        "url": "https:\/\/pemilu2024.kpu.go.id\/pilpres\/hitung-suara\/33\/3312\/331213\/3312132001\/3312132001012"
    },
    {
        "provinsi": "33",
        "kabupaten": "3312",
        "kecamatan": "331213",
        "desa": "3312132007",
        "tps": "3312132007001",
        "nama": "TPS 001, NGADIROJO LOR, NGADIROJO, WONOGIRI, JAWA TENGAH",
        "selisih": -4,
        "url": "https:\/\/pemilu2024.kpu.go.id\/pilpres\/hitung-suara\/33\/3312\/331213\/3312132007\/3312132007001"
    },
    {
        "provinsi": "33",
        "kabupaten": "3312",
        "kecamatan": "331213",
        "desa": "3312132007",
        "tps": "3312132007012",
        "nama": "TPS 012, NGADIROJO LOR, NGADIROJO, WONOGIRI, JAWA TENGAH",
        "selisih": 41,
        "url": "https:\/\/pemilu2024.kpu.go.id\/pilpres\/hitung-suara\/33\/3312\/331213\/3312132007\/3312132007012"
    },
    {
        "provinsi": "33",
        "kabupaten": "3312",
        "kecamatan": "331213",
        "desa": "3312132004",
        "tps": "3312132004007",
        "nama": "TPS 007, PONDOK, NGADIROJO, WONOGIRI, JAWA TENGAH",
        "selisih": 172,
        "url": "https:\/\/pemilu2024.kpu.go.id\/pilpres\/hitung-suara\/33\/3312\/331213\/3312132004\/3312132004007"
    },
    {
        "provinsi": "33",
        "kabupaten": "3312",
        "kecamatan": "331206",
        "desa": "3312062007",
        "tps": "3312062007003",
        "nama": "TPS 003, GEBANG, NGUNTORONADI, WONOGIRI, JAWA TENGAH",
        "selisih": -2,
        "url": "https:\/\/pemilu2024.kpu.go.id\/pilpres\/hitung-suara\/33\/3312\/331206\/3312062007\/3312062007003"
    },
    {
        "provinsi": "33",
        "kabupaten": "3312",
        "kecamatan": "331201",
        "desa": "3312012012",
        "tps": "3312012012005",
        "nama": "TPS 005, BANARAN, PRACIMANTORO, WONOGIRI, JAWA TENGAH",
        "selisih": 1,
        "url": "https:\/\/pemilu2024.kpu.go.id\/pilpres\/hitung-suara\/33\/3312\/331201\/3312012012\/3312012012005"
    },
    {
        "provinsi": "33",
        "kabupaten": "3312",
        "kecamatan": "331217",
        "desa": "3312172013",
        "tps": "3312172013003",
        "nama": "TPS 003, SENDANG, PURWANTORO, WONOGIRI, JAWA TENGAH",
        "selisih": 4,
        "url": "https:\/\/pemilu2024.kpu.go.id\/pilpres\/hitung-suara\/33\/3312\/331217\/3312172013\/3312172013003"
    },
    {
        "provinsi": "33",
        "kabupaten": "3312",
        "kecamatan": "331211",
        "desa": "3312112009",
        "tps": "3312112009013",
        "nama": "TPS 013, JATEN, SELOGIRI, WONOGIRI, JAWA TENGAH",
        "selisih": -6,
        "url": "https:\/\/pemilu2024.kpu.go.id\/pilpres\/hitung-suara\/33\/3312\/331211\/3312112009\/3312112009013"
    },
    {
        "provinsi": "33",
        "kabupaten": "3312",
        "kecamatan": "331211",
        "desa": "3312112006",
        "tps": "3312112006014",
        "nama": "TPS 014, SINGODUTAN, SELOGIRI, WONOGIRI, JAWA TENGAH",
        "selisih": 5,
        "url": "https:\/\/pemilu2024.kpu.go.id\/pilpres\/hitung-suara\/33\/3312\/331211\/3312112006\/3312112006014"
    },
    {
        "provinsi": "33",
        "kabupaten": "3312",
        "kecamatan": "331214",
        "desa": "3312142007",
        "tps": "3312142007002",
        "nama": "TPS 002, NGABEYAN, SIDOHARJO, WONOGIRI, JAWA TENGAH",
        "selisih": 107,
        "url": "https:\/\/pemilu2024.kpu.go.id\/pilpres\/hitung-suara\/33\/3312\/331214\/3312142007\/3312142007002"
    },
    {
        "provinsi": "33",
        "kabupaten": "3312",
        "kecamatan": "331214",
        "desa": "3312142003",
        "tps": "3312142003004",
        "nama": "TPS 004, TEMPURSARI, SIDOHARJO, WONOGIRI, JAWA TENGAH",
        "selisih": 5,
        "url": "https:\/\/pemilu2024.kpu.go.id\/pilpres\/hitung-suara\/33\/3312\/331214\/3312142003\/3312142003004"
    },
    {
        "provinsi": "33",
        "kabupaten": "3312",
        "kecamatan": "331205",
        "desa": "3312052006",
        "tps": "3312052006002",
        "nama": "TPS 002, SIDOREJO, TIRTOMOYO, WONOGIRI, JAWA TENGAH",
        "selisih": 29,
        "url": "https:\/\/pemilu2024.kpu.go.id\/pilpres\/hitung-suara\/33\/3312\/331205\/3312052006\/3312052006002"
    },
    {
        "provinsi": "33",
        "kabupaten": "3312",
        "kecamatan": "331205",
        "desa": "3312052006",
        "tps": "3312052006009",
        "nama": "TPS 009, SIDOREJO, TIRTOMOYO, WONOGIRI, JAWA TENGAH",
        "selisih": -80,
        "url": "https:\/\/pemilu2024.kpu.go.id\/pilpres\/hitung-suara\/33\/3312\/331205\/3312052006\/3312052006009"
    },
    {
        "provinsi": "33",
        "kabupaten": "3312",
        "kecamatan": "331212",
        "desa": "3312122012",
        "tps": "3312122012009",
        "nama": "TPS 009, MANJUNG, WONOGIRI, WONOGIRI, JAWA TENGAH",
        "selisih": 1,
        "url": "https:\/\/pemilu2024.kpu.go.id\/pilpres\/hitung-suara\/33\/3312\/331212\/3312122012\/3312122012009"
    },
    {
        "provinsi": "33",
        "kabupaten": "3312",
        "kecamatan": "331212",
        "desa": "3312122009",
        "tps": "3312122009005",
        "nama": "TPS 005, BULUSULUR, WONOGIRI, WONOGIRI, JAWA TENGAH",
        "selisih": 29,
        "url": "https:\/\/pemilu2024.kpu.go.id\/pilpres\/hitung-suara\/33\/3312\/331212\/3312122009\/3312122009005"
    },
    {
        "provinsi": "33",
        "kabupaten": "3312",
        "kecamatan": "331212",
        "desa": "3312122009",
        "tps": "3312122009005",
        "nama": "TPS 005, BULUSULUR, WONOGIRI, WONOGIRI, JAWA TENGAH",
        "selisih": -80,
        "url": "https:\/\/pemilu2024.kpu.go.id\/pilpres\/hitung-suara\/33\/3312\/331212\/3312122009\/3312122009005"
    }
]